Workbook

Sheet 00_Cover
B2: WORKING CAPITAL DIAGNOSTIC - NHUA HA NOI (HNX: NHH)
B4: Cash conversion cycle analysis FY2023-FY2025, benchmarked against listed plastics contract manufacturers in Malaysia, Japan and Sweden.
B6: SHEET INDEX
B7: Sheet | C7: Description
B8: 00_Cover | C8: Project information, colour legend, sheet index, changelog
B9: 01_Inputs | C9: NHH consolidated audited financials - all hardcoded input
B10: 02_Assumptions | C10: Drivers: days in period, CCC sensitivity scenarios
B11: 03_FS_Restated | C11: VAS financials restated to an analytical format
B12: 04_Ratios | C12: Liquidity, profitability, efficiency, leverage, DuPont
B13: 05_CCC | C13: CCC decomposition, average-balance basis, sensitivity, purchases-basis DPO check
B14: 06_Peer_Inputs | C14: Peer financials as reported, own currency, with extraction notes
B15: 07_Peer_Benchmark | C15: Peer CCC comparison, payables gap and cash-release quantification
B16: 08_Dashboard | C16: One-page executive summary
B17: 09_Reference | C17: Glossary EN-VN, account codes, methodology notes

Sheet 01_Inputs
B2: 01 - INPUT: FINANCIAL STATEMENTS, 3 YEARS (RAW)
B3: Unit: VND TK = VAS account code (Circular 200/2014/TT-BTC)
B5: Khoản mục | C5: TK | D5: FY2023 | E5: FY2024 | F5: FY2025
B6: A. BALANCE SHEET (as reported under Circular 200)
B7: TÀI SẢN NGẮN HẠN | C7: 100 | D7: 833749782499 | E7: 835183275843 | F7: 1108594044712
B8: Tiền và tương đương tiền | C8: 110 | D8: 68340657663 | E8: 191950270642 | F8: 346419887547
B9: Tiền mặt | C9: 111 | D9: 50790657663 | E9: 141391023267 | F9: 70123117547
B10: Tiền gửi ngân hàng | C10: 112 | D10: 17550000000 | E10: 50559247375 | F10: 276296770000
B11: Đầu tư tài chính ngắn hạn | C11: 120 | D11: 200192000000 | E11: 760062000 | F11: 119400000000
B12: Các khoản phải thu ngắn hạn | C12: 130 | D12: 294940405706 | E12: 378616624372 | F12: 336704878047
B13: Phải thu khách hàng | C13: 131 | D13: 225698917511 | E13: 298853660085 | F13: 281041557777
B14: Trả trước cho người bán | C14: 331_prepaid | D14: 32932283075 | E14: 25921034452 | F14: 37330026835
B15: Phải thu khác (gồm cho vay NH) | C15: 138 | D15: 37912057096 | E15: 57480648816 | F15: 21972012416
B16: Dự phòng phải thu khó đòi (−) | C16: 139 | D16: 1602851976 | E16: 3638718981 | F16: 3638718981
B17: Hàng tồn kho | C17: 140 | D17: 230582555144 | E17: 218749159456 | F17: 239364939489
B18: Nguyên vật liệu (NVL) | C18: 152 | D18: 110619487264 | E18: 109617529820 | F18: 109141860273
... B26: Tài sản cố định (net) | C26: 220 | D26: 798732153906 | E26: 828896685347 | F26: 890389773268
B27: Nguyên giá TSCĐ | C27: 211 | D27: =1508242011291+80861261462+16211789411 -> 1605315062164 | E27: =1638307185351+69632760488+17164966365 -> 1725104912204 | F27: =1817746990805+40976150806+17649966365 -> 1876373107976
B28: Hao mòn luỹ kế TSCĐ (−) | C28: 214 | D28: =784786741867+12229433796+9566732595 -> 806582908258 | E28: =873652935714+12824054943+9731236200 -> 896208226857 | F28: =965248776530+8308587940+12425970238 -> 985983334708
B29: Phải thu DH + Tài sản dở dang DH | C29: 210_240 | D29: 7266648143 | E29: 6621174710 | F29: 284677722914
B30: Đầu tư tài chính dài hạn | C30: 250 | D30: 299132386348 | E30: 117453931611 | F30: 58184439385
B31: Tài sản dài hạn khác | C31: 260 | D31: 137748858693 | E31: 142076071835 | F31: 187354280183
B32: TỔNG CỘNG TÀI SẢN | C32: 270 | D32: 2076629829589 | E32: 1930231139346 | F32: 2529200260462
B34: NỢ PHẢI TRẢ | C34: 300 | D34: 703411896251 | E34: 573685486036 | F34: 703597445053
B35: Nợ ngắn hạn | C35: 310 | D35: 666286577823 | E35: 511697586717 | F35: 608751653213
B36: Phải trả người bán | C36: 331 | D36: 126460714750 | E36: 151502988335 | F36: 183920068898
B37: Người mua trả tiền trước | C37: 131_advance | D37: 20890314563 | E37: 11074253824 | F37: 35223524344
B38: Thuế và các khoản phải nộp NN | C38: 333 | D38: 9476493621 | E38: 19713181099 | F38: 28650748806
B39: Phải trả người lao động | C39: 334 | D39: 22163048875 | E39: 25057547792 | F39: 25134675997
B40: Chi phí phải trả | C40: 335 | D40: 24260845667 | E40: 29760842941 | F40: 39249725925
B41: Vay và nợ thuê tài chính NH | C41: 341_short | D41: 448650974237 | E41: 244959596102 | F41: 235224392726
... B51: TỔNG NGUỒN VỐN | C51: 440 | D51: 2076629829589 | E51: 1930231139346 | F51: 2529200260462
B52: Check: Total assets - Total liabilities and equity | D52: =D32-D51 -> 0 | E52: =E32-E51 -> 0 | F52: =F32-F51 -> 0
B55: B. INCOME STATEMENT (as reported under Circular 200)
B56: Doanh thu bán hàng và CCDV | C56: 511 | D56: 2040961680650 | E56: 2098726472452 | F56: 2313527757468
B57: Các khoản giảm trừ doanh thu | C57: 521 | D57: 1676922497 | E57: 1821019812 | F57: 2322804549
B58: Doanh thu thuần | C58: 10 | D58: 2039284758153 | E58: 2096905452640 | F58: 2311204952919
B59: Giá vốn hàng bán (COGS) | C59: 632 | D59: 1736658116472 | E59: 1706260890180 | F59: 1912082184770
B60: Lợi nhuận gộp | C60: 20 | D60: 302626641681 | E60: 390644562460 | F60: 399122768149
B61: Doanh thu hoạt động tài chính | C61: 515 | D61: 36269307014 | E61: 32026200197 | F61: 35058145517
B62: Chi phí tài chính | C62: 635 | D62: 50164360653 | E62: 32499247742 | F62: 37141382228
B63: Trong đó: chi phí lãi vay | C63: 635_int | D63: 45942326390 | E63: 21203575185 | F63: 16100394821
B64: Chi phí bán hàng | C64: 641 | D64: 92582404275 | E64: 129255674644 | F64: 133870768647
B65: Chi phí quản lý doanh nghiệp | C65: 642 | D65: 73591545890 | E65: 83243116647 | F65: 100811309874
B66: Lợi nhuận thuần từ HĐKD | C66: 30 | D66: 117070651554 | E66: 112348581626 | F66: 161010452347
B67: Thu nhập khác | C67: 711 | D67: 5088405237 | E67: 3336091731 | F67: 5917485478
... B73: Khấu hao trong kỳ (D&A) | C73: 214_dep | D73: 110772493394 | E73: 107615606434 | F73: 115911638400
B74: EBITDA (calc) | C74: — | D74: =D66+D73 -> 227843144948 | E74: =E66+E73 -> 219964188060 | F74: =F66+F73 -> 276922090747
B77: C. CASH FLOW STATEMENT - indirect method
B78: I. LƯU CHUYỂN TỪ HOẠT ĐỘNG KINH DOANH
B79: Lợi nhuận trước thuế | C79: 01 | D79: 120543242466 | E79: 111470539520 | F79: 161883838293
B80: Điều chỉnh: Khấu hao | C80: 02 | D80: 110772493394 | E80: 107615606434 | F80: 115911638400
B81: Điều chỉnh: Dự phòng | C81: 03 | D81: -363806619 | E81: 914488062 | F81: 605118037
B82: Điều chỉnh: Lãi lỗ chênh lệch tỷ giá | C82: 04 | D82: -450056865 | E82: -265444275 | F82: 26349736
B83: Điều chỉnh: Lãi lỗ HĐ đầu tư | C83: 05 | D83: -21407367201 | E83: 56098519538 | F83: -2462934274
B84: Điều chỉnh: Chi phí lãi vay | C84: 06 | D84: 45942326390 | E84: 21358747599 | F84: 16410739649
B85: LN từ HĐKD trước thay đổi VLĐ | C85: 08 | D85: 255036831565 | E85: 297192456878 | F85: 292374749841
B86: (±) Tăng giảm các khoản phải thu | C86: 09 | D86: 189363608374 | E86: -65337146518 | F86: -42276935877
B87: (±) Tăng giảm hàng tồn kho | C87: 10 | D87: 137979479911 | E87: 12954774631 | F87: -21220898070
B88: (±) Tăng giảm các khoản phải trả | C88: 11 | D88: -183479626480 | E88: 18941132594 | F88: 85769542074
B89: (±) Tăng giảm chi phí trả trước | C89: 12 | D89: 10328511370 | E89: -6116105917 | F89: -47244872956
B90: Tiền lãi vay đã trả | C90: 14 | D90: -46196944418 | E90: -22007677332 | F90: -16163958407
... B92: LC thuần từ HĐKD (CFO) | C92: 20 | D92: 317747389510 | E92: 221025828996 | F92: 214122633014
B93: II. LƯU CHUYỂN TỪ HOẠT ĐỘNG ĐẦU TƯ
B94: Chi mua sắm TSCĐ (Capex) | C94: 21 | D94: -48578902991 | E94: -138500262248 | F94: -437697616704
B95: Thu từ thanh lý TSCĐ | C95: 22 | D95: 2349410170 | E95: 21132077297 | F95: 2371594968
B96: LC thuần từ HĐ ĐT (CFI) | C96: 30 | D96: -358031210636 | E96: 134441568375 | F96: -446906554372
B97: III. LƯU CHUYỂN TỪ HOẠT ĐỘNG TÀI CHÍNH
B98: Thu từ phát hành cổ phiếu/góp vốn | C98: 31 | D98: 0 | E98: 0 | F98: 363954400000
B99: Thu từ đi vay | C99: 33 | D99: 1112681371857 | E99: 839154407789 | F99: 508896818236
B100: Trả nợ gốc vay | C100: 34 | D100: -1325226742983 | E100: -1034623011507 | F100: -485961279091
B101: Cổ tức đã trả | C101: 36 | D101: -36433000000 | E101: -36433000000 | F101: 0
B102: LC thuần từ HĐ TC (CFF) | C102: 40 | D102: =SUM(D98:D101) -> -248978371126 | E102: =SUM(E98:E101) -> -231901603718 | F102: =SUM(F98:F101) -> 386889939145
B103: LC thuần trong kỳ (CFO+CFI+CFF) | C103: 50 | D103: =D92+D96+D102 -> -289262192252 | E103: =E92+E96+E102 -> 123565793653 | F103: =F92+F96+F102 -> 154106017787
B104: Tiền đầu kỳ | C104: 60 | D104: 357140742117 | E104: 68340657663 | F104: 191950270642
B105: Tiền cuối kỳ (= dòng 8) | C105: 70 | D105: =D8 -> 68340657663 | E105: =E8 -> 191950270642 | F105: =F8 -> 346419887547
B107: D. INTERNAL CONSISTENCY CHECKS (=0)
B108: Check | D108: FY2023 | E108: FY2024 | F108: FY2025
B109: MS 100 = 110+120+130+140+150 | D109: =D7-(D8+D11+D12+D17+D24) -> 0 | E109: =E7-(E8+E11+E12+E17+E24) -> 0 | F109: =F7-(F8+F11+F12+F17+F24) -> 0
B110: MS 130 = 131 + 132 + other receivables - 139 | D110: =D12-(D13+D14+D15-D16) -> 0 | E110: =E12-(E13+E14+E15-E16) -> 0 | F110: =F12-(F13+F14+F15-F16) -> 0
B111: MS 140 = inventory components - 159 | D111: =D17-(D18+D19+D20+D21+D22-D23) -> 0 | E111: =E17-(E18+E19+E20+E21+E22-E23) -> 0 | F111: =F17-(F18+F19+F20+F21+F22-F23) -> 0
B112: MS 220 = gross fixed assets - accumulated depreciation | D112: =D26-(D27-D28) -> 0 | E112: =E26-(E27-E28) -> 0 | F112: =F26-(F27-F28) -> 0
B113: MS 200 = 220+(210_240)+250+260 | D113: =D25-(D26+D29+D30+D31) -> 0 | E113: =E25-(E26+E29+E30+E31) -> 0 | F113: =F25-(F26+F29+F30+F31) -> 0
B114: MS 270 = 100 + 200 | D114: =D32-(D7+D25) -> 0 | E114: =E32-(E7+E25) -> 0 | F114: =F32-(F7+F25) -> 0
B115: MS 310 = total current liabilities | D115: =D35-SUM(D36:D42) -> 0 | E115: =E35-SUM(E36:E42) -> 0 | F115: =F35-SUM(F36:F42) -> 0
B116: MS 300 = 310 + 330 | D116: =D34-(D35+D43) -> 0 | E116: =E34-(E35+E43) -> 0 | F116: =F34-(F35+F43) -> 0
B117: MS 400 = equity components + non-controlling interests | D117: =D46-(D47+D48+D49+D50+D45) -> 0 | E117: =E46-(E47+E48+E49+E50+E45) -> 0 | F117: =F46-(F47+F48+F49+F50+F45) -> 0
B118: MS 440 = 300 + 400 | D118: =D51-(D34+D46) -> 0 | E118: =E51-(E34+E46) -> 0 | F118: =F51-(F34+F46) -> 0
B119: Total assets - total liabilities and equity | D119: =D32-D51 -> 0 | E119: =E32-E51 -> 0 | F119: =F32-F51 -> 0
B120: MS 10 = 511 - 521 | D120: =D58-(D56-D57) -> 0 | E120: =E58-(E56-E57) -> 0 | F120: =F58-(F56-F57) -> 0
B121: MS 20 = 10 - 632 | D121: =D60-(D58-D59) -> 0 | E121: =E60-(E58-E59) -> 0 | F121: =F60-(F58-F59) -> 0
B122: MS 30 = 20+515-635-24-641-642 | D122: =D66-(D60+D61-D62-D72-D64-D65) -> 0 | E122: =E66-(E60+E61-E62-E72-E64-E65) -> 0 | F122: =F66-(F60+F61-F62-F72-F64-F65) -> 0
B123: MS 50 = 30+711-811 | D123: =D69-(D66+D67-D68) -> 0 | E123: =E69-(E66+E67-E68) -> 0 | F123: =F69-(F66+F67-F68) -> 0
B124: MS 60 = MS 50 - corporate income tax | D124: =D71-(D69-D70) -> 0 | E124: =E71-(E69-E70) -> 0 | F124: =F71-(F69-F70) -> 0
B125: CFF (40) = 31+33+34+36 | D125: =D102-(D98+D99+D100+D101) -> 0 | E125: =E102-(E98+E99+E100+E101) -> 0 | F125: =F102-(F98+F99+F100+F101) -> 0
B126: Net cash flow (MS 50) = CFO + CFI + CFF | D126: =D103-(D92+D96+D102) -> 0 | E126: =E103-(E92+E96+E102) -> 0 | F126: =F103-(F92+F96+F102) -> 0

Sheet 02_Assumptions
B2: 02 — ASSUMPTIONS & DRIVERS
B5: Driver | C5: Base | D5: Low | E5: High | F5: Note
B6: A. RECEIVABLES AGEING - BUCKET THRESHOLDS (days)
B7: Bucket 1 (current) - upper limit | C7: 30 | D7: 30 | E7: 30 | F7: 0-30 days
B8: Bucket 2 - upper limit | C8: 60 | D8: 60 | E8: 60 | F8: 31-60 days
B9: Bucket 3 - upper limit | C9: 90 | D9: 90 | E9: 90 | F9: 61-90 days
B10: Bucket 4 - upper limit | C10: 180 | D10: 180 | E10: 180 | F10: 91-180 days
B11: Bucket 5 (Long overdue) | C11: 999 | D11: 999 | E11: 999 | F11: Over 180 days - red flag
B12: Provisioning threshold (%) | C12: 0.005 | D12: 0.005 | E12: 0.005 | F12: Example: 0.5% for 61-90 days, per Circular 48/2019/TT-BTC
B14: B. CCC SENSITIVITY (change in days to VND released)
B15: ∆CCC scenario 1 (days) | C15: -5 | F15: Modest improvement
B16: ∆CCC scenario 2 (days) | C16: -10 | F16: Moderate improvement
B17: ∆CCC scenario 3 (days) | C17: -15 | F17: Strong improvement - best case
B18: ∆CCC scenario 4 (days) | C18: 5 | F18: Deterioration - worst case
B20: C. CASH FORECAST — DRIVERS
B21: Minimum closing cash threshold (VND) | C21: 5000000000 | D21: 3000000000 | E21: 10000000000 | F21: Below this threshold - red flag
B22: Contractual DSO, Honda (days) | C22: 60 | D22: 45 | E22: 90 | F22: Contract terms - to be confirmed with sales
B23: Contractual DSO, Samsung (days) | C23: 60 | D23: 45 | E23: 90 | F23: Contract terms - to be confirmed with sales
B24: Contractual DSO, other customers (days) | C24: 45 | D24: 30 | E24: 60
B25: Contractual DPO, domestic suppliers | C25: 30 | D25: 15 | E25: 45
B26: Contractual DPO, import suppliers | C26: 60 | D26: 30 | E26: 90 | F26: Letter of credit or telegraphic transfer
B27: Collection rate, week 1 after invoice (%) | C27: 0.05 | D27: 0 | E27: 0.1 | F27: Empirical, from observed collection pattern
B28: Collection rate, weeks 4-8 (%) | C28: 0.6 | D28: 0.4 | E28: 0.8
B29: Collection rate, weeks 8-13 (%) | C29: 0.3 | D29: 0.15 | E29: 0.4
B30: % bad debt / uncollectible | C30: 0.02 | D30: 0 | E30: 0.05
B31: Payroll cycle (day of month) | C31: 5 | D31: 1 | E31: 10 | F31: Regular payroll date
B32: Tax payment cycle | C32: 20 | D32: 20 | E32: 20 | F32: VAT and personal income tax remittance - 20th of the following month
B34: D. INVENTORY ABC - PARETO THRESHOLDS
B35: Class A - cumulative value ceiling (%) | C35: 0.8 | D35: 0.75 | E35: 0.85 | F35: Approximately 80% of value
B36: Class B - cumulative value ceiling (%) | C36: 0.95 | D36: 0.9 | E36: 0.97 | F36: 80-95% of value
B37: Class C - remainder (automatic) | C37: 1 | D37: 1 | E37: 1 | F37: >95%
B38: Cycle count frequency, class A (days) | C38: 7 | D38: 7 | E38: 14 | F38: Weekly
B39: Cycle count frequency, class B (days) | C39: 30 | D39: 30 | E39: 30 | F39: Monthly
B40: Cycle count frequency, class C (days) | C40: 90 | D40: 90 | E40: 90 | F40: Quarterly
B42: E. GENERAL
B43: Days per year | C43: 365 | D43: 360 | E43: 365 | F43: Finance convention: 365. Vietnamese practice often uses 360.
B44: Dashboard display unit | C44: VND billion | F44: 'VND billion' or 'VND million'
B46: F. TAX & COST OF CAPITAL
B47: Tax rate for NOPAT (ROIC) | C47: 0.2 | F47: Vietnamese statutory CIT rate. Compare with the effective rate below.

Sheet 03_FS_Restated
B2: 03 — FS RESTATED (Balance Sheet + IS + Common-Size)
B5: Line item | C5: FY2023 | D5: FY2024 | E5: FY2025 | F5: %FY23 | G5: %FY24 | H5: %FY25
A6: A. BALANCE SHEET - analytical format
B7: Cash and equivalents | C7: =IFERROR(INDEX('01_Inputs'!D:D,MATCH("110",'01_Inputs'!C:C,0)),0) -> 68340657663 | D7: =IFERROR(INDEX('01_Inputs'!E:E,MATCH("110",'01_Inputs'!C:C,0)),0) -> 191950270642 | E7: =IFERROR(INDEX('01_Inputs'!F:F,MATCH("110",'01_Inputs'!C:C,0)),0) -> 346419887547 | F7: =IFERROR(C7/C$18,0) -> 0.032909408 | G7: =IFERROR(D7/D$18,0) -> 0.099444189 | H7: =IFERROR(E7/E$18,0) -> 0.13696815
B8: Short-term investments | C8: =IFERROR(INDEX('01_Inputs'!D:D,MATCH("120",'01_Inputs'!C:C,0)),0) -> 200192000000 | D8: =IFERROR(INDEX('01_Inputs'!E:E,MATCH("120",'01_Inputs'!C:C,0)),0) -> 760062000 | E8: =IFERROR(INDEX('01_Inputs'!F:F,MATCH("120",'01_Inputs'!C:C,0)),0) -> 119400000000 | F8: =IFERROR(C8/C$18,0) -> 0.096402352 | G8: =IFERROR(D8/D$18,0) -> 0.00039376735 | H8: =IFERROR(E8/E$18,0) -> 0.047208599
B9: Accounts Receivable (AR) | C9: =IFERROR(INDEX('01_Inputs'!D:D,MATCH("131",'01_Inputs'!C:C,0)),0) -> 225698917511 | D9: =IFERROR(INDEX('01_Inputs'!E:E,MATCH("131",'01_Inputs'!C:C,0)),0) -> 298853660085 | E9: =IFERROR(INDEX('01_Inputs'!F:F,MATCH("131",'01_Inputs'!C:C,0)),0) -> 281041557777 | F9: =IFERROR(C9/C$18,0) -> 0.10868519 | G9: =IFERROR(D9/D$18,0) -> 0.15482791 | H9: =IFERROR(E9/E$18,0) -> 0.11111874
B10: Inventory — Raw Material (NVL) | C10: =IFERROR(INDEX('01_Inputs'!D:D,MATCH("152",'01_Inputs'!C:C,0)),0) -> 110619487264 | D10: =IFERROR(INDEX('01_Inputs'!E:E,MATCH("152",'01_Inputs'!C:C,0)),0) -> 109617529820 | E10: =IFERROR(INDEX('01_Inputs'!F:F,MATCH("152",'01_Inputs'!C:C,0)),0) -> 109141860273 | F10: =IFERROR(C10/C$18,0) -> 0.053268756 | G10: =IFERROR(D10/D$18,0) -> 0.056789846 | H10: =IFERROR(E10/E$18,0) -> 0.043152716
B11: Inventory — Work in Progress (WIP) | C11: =IFERROR(INDEX('01_Inputs'!D:D,MATCH("154",'01_Inputs'!C:C,0)),0) -> 49989085832 | D11: =IFERROR(INDEX('01_Inputs'!E:E,MATCH("154",'01_Inputs'!C:C,0)),0) -> 46501449750 | E11: =IFERROR(INDEX('01_Inputs'!F:F,MATCH("154",'01_Inputs'!C:C,0)),0) -> 55423165622 | F11: =IFERROR(C11/C$18,0) -> 0.024072218 | G11: =IFERROR(D11/D$18,0) -> 0.02409113 | H11: =IFERROR(E11/E$18,0) -> 0.021913316
B12: Inventory — Finished Goods (FG) | C12: =IFERROR(INDEX('01_Inputs'!D:D,MATCH("155",'01_Inputs'!C:C,0)),0) -> 60251021462 | D12: =IFERROR(INDEX('01_Inputs'!E:E,MATCH("155",'01_Inputs'!C:C,0)),0) -> 49413042824 | E12: =IFERROR(INDEX('01_Inputs'!F:F,MATCH("155",'01_Inputs'!C:C,0)),0) -> 58450225920 | F12: =IFERROR(C12/C$18,0) -> 0.029013848 | G12: =IFERROR(D12/D$18,0) -> 0.025599547 | H12: =IFERROR(E12/E$18,0) -> 0.023110161
B13: Inventory — Total | C13: =IFERROR(INDEX('01_Inputs'!D:D,MATCH("140",'01_Inputs'!C:C,0)),0) -> 230582555144 | D13: =IFERROR(INDEX('01_Inputs'!E:E,MATCH("140",'01_Inputs'!C:C,0)),0) -> 218749159456 | E13: =IFERROR(INDEX('01_Inputs'!F:F,MATCH("140",'01_Inputs'!C:C,0)),0) -> 239364939489 | F13: =IFERROR(C13/C$18,0) -> 0.11103691 | G13: =IFERROR(D13/D$18,0) -> 0.11332796 | H13: =IFERROR(E13/E$18,0) -> 0.094640564
B14: Other current assets | C14: =IFERROR(INDEX('01_Inputs'!D:D,MATCH("150",'01_Inputs'!C:C,0)),0) -> 39694163986 | D14: =IFERROR(INDEX('01_Inputs'!E:E,MATCH("150",'01_Inputs'!C:C,0)),0) -> 45107159373 | E14: =IFERROR(INDEX('01_Inputs'!F:F,MATCH("150",'01_Inputs'!C:C,0)),0) -> 66704339629 | F14: =IFERROR(C14/C$18,0) -> 0.019114704 | G14: =IFERROR(D14/D$18,0) -> 0.023368786 | H14: =IFERROR(E14/E$18,0) -> 0.026373688
B15: TOTAL CURRENT ASSETS | C15: =IFERROR(INDEX('01_Inputs'!D:D,MATCH("100",'01_Inputs'!C:C,0)),0) -> 833749782499 | D15: =IFERROR(INDEX('01_Inputs'!E:E,MATCH("100",'01_Inputs'!C:C,0)),0) -> 835183275843 | E15: =IFERROR(INDEX('01_Inputs'!F:F,MATCH("100",'01_Inputs'!C:C,0)),0) -> 1108594044712 | F15: =IFERROR(C15/C$18,0) -> 0.40149177 | G15: =IFERROR(D15/D$18,0) -> 0.43268563 | H15: =IFERROR(E15/E$18,0) -> 0.43831802
B16: Fixed Assets — Net | C16: =IFERROR(INDEX('01_Inputs'!D:D,MATCH("220",'01_Inputs'!C:C,0)),0) -> 798732153906 | D16: =IFERROR(INDEX('01_Inputs'!E:E,MATCH("220",'01_Inputs'!C:C,0)),0) -> 828896685347 | E16: =IFERROR(INDEX('01_Inputs'!F:F,MATCH("220",'01_Inputs'!C:C,0)),0) -> 890389773268 | F16: =IFERROR(C16/C$18,0) -> 0.38462905 | G16: =IFERROR(D16/D$18,0) -> 0.42942872 | H16: =IFERROR(E16/E$18,0) -> 0.352044
B17: Other non-current assets (LT receivables, CIP, LT investments, other) | C17: =IFERROR(INDEX('01_Inputs'!D:D,MATCH("210_240",'01_Inputs'!C:C,0)),0)+IFERROR(INDEX('01_Inputs'!D:D,MATCH("250",'01_Inputs'!C:C,0)),0)+IFERROR(INDEX('01_Inputs'!D:D,MATCH("260",'01_Inputs'!C:C,0)),0) -> 444147893184 | D17: =IFERROR(INDEX('01_Inputs'!E:E,MATCH("210_240",'01_Inputs'!C:C,0)),0)+IFERROR(INDEX('01_Inputs'!E:E,MATCH("250",'01_Inputs'!C:C,0)),0)+IFERROR(INDEX('01_Inputs'!E:E,MATCH("260",'01_Inputs'!C:C,0)),0) -> 266151178156 | E17: =IFERROR(INDEX('01_Inputs'!F:F,MATCH("210_240",'01_Inputs'!C:C,0)),0)+IFERROR(INDEX('01_Inputs'!F:F,MATCH("250",'01_Inputs'!C:C,0)),0)+IFERROR(INDEX('01_Inputs'!F:F,MATCH("260",'01_Inputs'!C:C,0)),0) -> 530216442482 | F17: =IFERROR(C17/C$18,0) -> 0.21387918 | G17: =IFERROR(D17/D$18,0) -> 0.13788565 | H17: =IFERROR(E17/E$18,0) -> 0.20963798
B18: TOTAL ASSETS | C18: =IFERROR(INDEX('01_Inputs'!D:D,MATCH("270",'01_Inputs'!C:C,0)),0) -> 2076629829589 | D18: =IFERROR(INDEX('01_Inputs'!E:E,MATCH("270",'01_Inputs'!C:C,0)),0) -> 1930231139346 | E18: =IFERROR(INDEX('01_Inputs'!F:F,MATCH("270",'01_Inputs'!C:C,0)),0) -> 2529200260462 | F18: =IFERROR(C18/C$18,0) -> 1 | G18: =IFERROR(D18/D$18,0) -> 1 | H18: =IFERROR(E18/E$18,0) -> 1
B19: Accounts Payable (AP) | C19: =IFERROR(INDEX('01_Inputs'!D:D,MATCH("331",'01_Inputs'!C:C,0)),0) -> 126460714750 | D19: =IFERROR(INDEX('01_Inputs'!E:E,MATCH("331",'01_Inputs'!C:C,0)),0) -> 151502988335 | E19: =IFERROR(INDEX('01_Inputs'!F:F,MATCH("331",'01_Inputs'!C:C,0)),0) -> 183920068898 | F19: =IFERROR(C19/C$18,0) -> 0.060897091 | G19: =IFERROR(D19/D$18,0) -> 0.078489558 | H19: =IFERROR(E19/E$18,0) -> 0.072718666
B20: Short-term debt | C20: =IFERROR(INDEX('01_Inputs'!D:D,MATCH("341_short",'01_Inputs'!C:C,0)),0) -> 448650974237 | D20: =IFERROR(INDEX('01_Inputs'!E:E,MATCH("341_short",'01_Inputs'!C:C,0)),0) -> 244959596102 | E20: =IFERROR(INDEX('01_Inputs'!F:F,MATCH("341_short",'01_Inputs'!C:C,0)),0) -> 235224392726 | F20: =IFERROR(C20/C$18,0) -> 0.21604764 | G20: =IFERROR(D20/D$18,0) -> 0.12690687 | H20: =IFERROR(E20/E$18,0) -> 0.093003467
B21: Other current liabilities | C21: =IFERROR(INDEX('01_Inputs'!D:D,MATCH("338",'01_Inputs'!C:C,0)),0) -> 14384186110 | D21: =IFERROR(INDEX('01_Inputs'!E:E,MATCH("338",'01_Inputs'!C:C,0)),0) -> 29629176624 | E21: =IFERROR(INDEX('01_Inputs'!F:F,MATCH("338",'01_Inputs'!C:C,0)),0) -> 61348516517 | F21: =IFERROR(C21/C$18,0) -> 0.0069266972 | G21: =IFERROR(D21/D$18,0) -> 0.015350067 | H21: =IFERROR(E21/E$18,0) -> 0.024256093
B22: TOTAL CURRENT LIABILITIES | C22: =IFERROR(INDEX('01_Inputs'!D:D,MATCH("310",'01_Inputs'!C:C,0)),0) -> 666286577823 | D22: =IFERROR(INDEX('01_Inputs'!E:E,MATCH("310",'01_Inputs'!C:C,0)),0) -> 511697586717 | E22: =IFERROR(INDEX('01_Inputs'!F:F,MATCH("310",'01_Inputs'!C:C,0)),0) -> 608751653213 | F22: =IFERROR(C22/C$18,0) -> 0.32084995 | G22: =IFERROR(D22/D$18,0) -> 0.26509653 | H22: =IFERROR(E22/E$18,0) -> 0.24068938
B23: Long-term debt | C23: =IFERROR(INDEX('01_Inputs'!D:D,MATCH("341_long",'01_Inputs'!C:C,0)),0) -> 37125318428 | D23: =IFERROR(INDEX('01_Inputs'!E:E,MATCH("341_long",'01_Inputs'!C:C,0)),0) -> 61987899319 | E23: =IFERROR(INDEX('01_Inputs'!F:F,MATCH("341_long",'01_Inputs'!C:C,0)),0) -> 94845791840 | F23: =IFERROR(C23/C$18,0) -> 0.017877678 | G23: =IFERROR(D23/D$18,0) -> 0.032114237 | H23: =IFERROR(E23/E$18,0) -> 0.037500309
B24: TOTAL LIABILITIES | C24: =IFERROR(INDEX('01_Inputs'!D:D,MATCH("300",'01_Inputs'!C:C,0)),0) -> 703411896251 | D24: =IFERROR(INDEX('01_Inputs'!E:E,MATCH("300",'01_Inputs'!C:C,0)),0) -> 573685486036 | E24: =IFERROR(INDEX('01_Inputs'!F:F,MATCH("300",'01_Inputs'!C:C,0)),0) -> 703597445053 | F24: =IFERROR(C24/C$18,0) -> 0.33872763 | G24: =IFERROR(D24/D$18,0) -> 0.29721077 | H24: =IFERROR(E24/E$18,0) -> 0.27818969
B25: TOTAL EQUITY | C25: =IFERROR(INDEX('01_Inputs'!D:D,MATCH("400",'01_Inputs'!C:C,0)),0) -> 1373217933338 | D25: =IFERROR(INDEX('01_Inputs'!E:E,MATCH("400",'01_Inputs'!C:C,0)),0) -> 1356545653310 | E25: =IFERROR(INDEX('01_Inputs'!F:F,MATCH("400",'01_Inputs'!C:C,0)),0) -> 1825602815409 | F25: =IFERROR(C25/C$18,0) -> 0.66127237 | G25: =IFERROR(D25/D$18,0) -> 0.70278923 | H25: =IFERROR(E25/E$18,0) -> 0.72181031
B26: CHECK: L+E vs TA | C26: =C24+C25-C18 -> 0 | D26: =D24+D25-D18 -> 0 | E26: =E24+E25-E18 -> 0
B27: CHECK: CA + FA + Other NCA vs TOTAL ASSETS | C27: =C15+C16+C17-C18 -> 0 | D27: =D15+D16+D17-D18 -> 0 | E27: =E15+E16+E17-E18 -> 0
A29: B. INCOME STATEMENT - analytical format
B30: Revenue (net) | C30: =IFERROR(INDEX('01_Inputs'!D:D,MATCH("10",'01_Inputs'!C:C,0)),0) -> 2039284758153 | D30: =IFERROR(INDEX('01_Inputs'!E:E,MATCH("10",'01_Inputs'!C:C,0)),0) -> 2096905452640 | E30: =IFERROR(INDEX('01_Inputs'!F:F,MATCH("10",'01_Inputs'!C:C,0)),0) -> 2311204952919 | F30: =IFERROR(C30/C$30,0) -> 1 | G30: =IFERROR(D30/D$30,0) -> 1 | H30: =IFERROR(E30/E$30,0) -> 1
B31: COGS | C31: =IFERROR(INDEX('01_Inputs'!D:D,MATCH("632",'01_Inputs'!C:C,0)),0) -> 1736658116472 | D31: =IFERROR(INDEX('01_Inputs'!E:E,MATCH("632",'01_Inputs'!C:C,0)),0) -> 1706260890180 | E31: =IFERROR(INDEX('01_Inputs'!F:F,MATCH("632",'01_Inputs'!C:C,0)),0) -> 1912082184770 | F31: =IFERROR(C31/C$30,0) -> 0.85160158 | G31: =IFERROR(D31/D$30,0) -> 0.81370426 | H31: =IFERROR(E31/E$30,0) -> 0.82730966
B32: Gross Profit | C32: =IFERROR(INDEX('01_Inputs'!D:D,MATCH("20",'01_Inputs'!C:C,0)),0) -> 302626641681 | D32: =IFERROR(INDEX('01_Inputs'!E:E,MATCH("20",'01_Inputs'!C:C,0)),0) -> 390644562460 | E32: =IFERROR(INDEX('01_Inputs'!F:F,MATCH("20",'01_Inputs'!C:C,0)),0) -> 399122768149 | F32: =IFERROR(C32/C$30,0) -> 0.14839842 | G32: =IFERROR(D32/D$30,0) -> 0.18629574 | H32: =IFERROR(E32/E$30,0) -> 0.17269034
B33: Selling expense | C33: =IFERROR(INDEX('01_Inputs'!D:D,MATCH("641",'01_Inputs'!C:C,0)),0) -> 92582404275 | D33: =IFERROR(INDEX('01_Inputs'!E:E,MATCH("641",'01_Inputs'!C:C,0)),0) -> 129255674644 | E33: =IFERROR(INDEX('01_Inputs'!F:F,MATCH("641",'01_Inputs'!C:C,0)),0) -> 133870768647 | F33: =IFERROR(C33/C$30,0) -> 0.045399449 | G33: =IFERROR(D33/D$30,0) -> 0.061641155 | H33: =IFERROR(E33/E$30,0) -> 0.0579225
B34: G&A expense | C34: =IFERROR(INDEX('01_Inputs'!D:D,MATCH("642",'01_Inputs'!C:C,0)),0) -> 73591545890 | D34: =IFERROR(INDEX('01_Inputs'!E:E,MATCH("642",'01_Inputs'!C:C,0)),0) -> 83243116647 | E34: =IFERROR(INDEX('01_Inputs'!F:F,MATCH("642",'01_Inputs'!C:C,0)),0) -> 100811309874 | F34: =IFERROR(C34/C$30,0) -> 0.03608694 | G34: =IFERROR(D34/D$30,0) -> 0.039698078 | H34: =IFERROR(E34/E$30,0) -> 0.043618507
B35: Financial income | C35: =IFERROR(INDEX('01_Inputs'!D:D,MATCH("515",'01_Inputs'!C:C,0)),0) -> 36269307014 | D35: =IFERROR(INDEX('01_Inputs'!E:E,MATCH("515",'01_Inputs'!C:C,0)),0) -> 32026200197 | E35: =IFERROR(INDEX('01_Inputs'!F:F,MATCH("515",'01_Inputs'!C:C,0)),0) -> 35058145517 | F35: =IFERROR(C35/C$30,0) -> 0.017785308 | G35: =IFERROR(D35/D$30,0) -> 0.015273078 | H35: =IFERROR(E35/E$30,0) -> 0.015168774
B36: Financial expense | C36: =IFERROR(INDEX('01_Inputs'!D:D,MATCH("635",'01_Inputs'!C:C,0)),0) -> 50164360653 | D36: =IFERROR(INDEX('01_Inputs'!E:E,MATCH("635",'01_Inputs'!C:C,0)),0) -> 32499247742 | E36: =IFERROR(INDEX('01_Inputs'!F:F,MATCH("635",'01_Inputs'!C:C,0)),0) -> 37141382228 | F36: =IFERROR(C36/C$30,0) -> 0.024598997 | G36: =IFERROR(D36/D$30,0) -> 0.015498671 | H36: =IFERROR(E36/E$30,0) -> 0.016070138
B37: o/w Interest expense | C37: =IFERROR(INDEX('01_Inputs'!D:D,MATCH("635_int",'01_Inputs'!C:C,0)),0) -> 45942326390 | D37: =IFERROR(INDEX('01_Inputs'!E:E,MATCH("635_int",'01_Inputs'!C:C,0)),0) -> 21203575185 | E37: =IFERROR(INDEX('01_Inputs'!F:F,MATCH("635_int",'01_Inputs'!C:C,0)),0) -> 16100394821 | F37: =IFERROR(C37/C$30,0) -> 0.022528647 | G37: =IFERROR(D37/D$30,0) -> 0.010111841 | H37: =IFERROR(E37/E$30,0) -> 0.0069662341
B38: Operating Profit | C38: =IFERROR(INDEX('01_Inputs'!D:D,MATCH("30",'01_Inputs'!C:C,0)),0) -> 117070651554 | D38: =IFERROR(INDEX('01_Inputs'!E:E,MATCH("30",'01_Inputs'!C:C,0)),0) -> 112348581626 | E38: =IFERROR(INDEX('01_Inputs'!F:F,MATCH("30",'01_Inputs'!C:C,0)),0) -> 161010452347 | F38: =IFERROR(C38/C$30,0) -> 0.057407702 | G38: =IFERROR(D38/D$30,0) -> 0.053578277 | H38: =IFERROR(E38/E$30,0) -> 0.069665155
B39: EBT | C39: =IFERROR(INDEX('01_Inputs'!D:D,MATCH("50",'01_Inputs'!C:C,0)),0) -> 120543242466 | D39: =IFERROR(INDEX('01_Inputs'!E:E,MATCH("50",'01_Inputs'!C:C,0)),0) -> 111470539520 | E39: =IFERROR(INDEX('01_Inputs'!F:F,MATCH("50",'01_Inputs'!C:C,0)),0) -> 161883838293 | F39: =IFERROR(C39/C$30,0) -> 0.059110549 | G39: =IFERROR(D39/D$30,0) -> 0.053159545 | H39: =IFERROR(E39/E$30,0) -> 0.070043047
B40: Tax expense | C40: =IFERROR(INDEX('01_Inputs'!D:D,MATCH("821",'01_Inputs'!C:C,0)),0) -> 24299989429 | D40: =IFERROR(INDEX('01_Inputs'!E:E,MATCH("821",'01_Inputs'!C:C,0)),0) -> 23615836329 | E40: =IFERROR(INDEX('01_Inputs'!F:F,MATCH("821",'01_Inputs'!C:C,0)),0) -> 42255969091 | F40: =IFERROR(C40/C$30,0) -> 0.011915937 | G40: =IFERROR(D40/D$30,0) -> 0.011262232 | H40: =IFERROR(E40/E$30,0) -> 0.01828309
B41: Net Income | C41: =IFERROR(INDEX('01_Inputs'!D:D,MATCH("60",'01_Inputs'!C:C,0)),0) -> 96243253037 | D41: =IFERROR(INDEX('01_Inputs'!E:E,MATCH("60",'01_Inputs'!C:C,0)),0) -> 87854703191 | E41: =IFERROR(INDEX('01_Inputs'!F:F,MATCH("60",'01_Inputs'!C:C,0)),0) -> 119627869202 | F41: =IFERROR(C41/C$30,0) -> 0.047194612 | G41: =IFERROR(D41/D$30,0) -> 0.041897313 | H41: =IFERROR(E41/E$30,0) -> 0.051759957
B42: D&A | C42: =IFERROR(INDEX('01_Inputs'!D:D,MATCH("214_dep",'01_Inputs'!C:C,0)),0) -> 110772493394 | D42: =IFERROR(INDEX('01_Inputs'!E:E,MATCH("214_dep",'01_Inputs'!C:C,0)),0) -> 107615606434 | E42: =IFERROR(INDEX('01_Inputs'!F:F,MATCH("214_dep",'01_Inputs'!C:C,0)),0) -> 115911638400 | F42: =IFERROR(C42/C$30,0) -> 0.054319287 | G42: =IFERROR(D42/D$30,0) -> 0.051321153 | H42: =IFERROR(E42/E$30,0) -> 0.050152038
B43: EBITDA | C43: =INDEX('03_FS_Restated'!C:C,MATCH("Operating Profit",'03_FS_Restated'!B:B,0))+INDEX('03_FS_Restated'!C:C,MATCH("D&A",'03_FS_Restated'!B:B,0)) -> 227843144948 | D43: =INDEX('03_FS_Restated'!D:D,MATCH("Operating Profit",'03_FS_Restated'!B:B,0))+INDEX('03_FS_Restated'!D:D,MATCH("D&A",'03_FS_Restated'!B:B,0)) -> 219964188060 | E43: =INDEX('03_FS_Restated'!E:E,MATCH("Operating Profit",'03_FS_Restated'!B:B,0))+INDEX('03_FS_Restated'!E:E,MATCH("D&A",'03_FS_Restated'!B:B,0)) -> 276922090747 | F43: =IFERROR(C43/C$30,0) -> 0.11172699 | G43: =IFERROR(D43/D$30,0) -> 0.10489943 | H43: =IFERROR(E43/E$30,0) -> 0.11981719
A45: C. WORKING CAPITAL SUMMARY
B46: Net Working Capital = CA − CL | C46: =IFERROR(INDEX(C:C,MATCH("TOTAL CURRENT ASSETS",B:B,0))-INDEX(C:C,MATCH("TOTAL CURRENT LIABILITIES",B:B,0)),0) -> 167463204676 | D46: =IFERROR(INDEX(D:D,MATCH("TOTAL CURRENT ASSETS",B:B,0))-INDEX(D:D,MATCH("TOTAL CURRENT LIABILITIES",B:B,0)),0) -> 323485689126 | E46: =IFERROR(INDEX(E:E,MATCH("TOTAL CURRENT ASSETS",B:B,0))-INDEX(E:E,MATCH("TOTAL CURRENT LIABILITIES",B:B,0)),0) -> 499842391499
B47: Operating NWC = AR + Inv − AP | C47: =IFERROR(INDEX(C:C,MATCH("Accounts Receivable (AR)",B:B,0))+INDEX(C:C,MATCH("Inventory — Total",B:B,0))-INDEX(C:C,MATCH("Accounts Payable (AP)",B:B,0)),0) -> 329820757905 | D47: =IFERROR(INDEX(D:D,MATCH("Accounts Receivable (AR)",B:B,0))+INDEX(D:D,MATCH("Inventory — Total",B:B,0))-INDEX(D:D,MATCH("Accounts Payable (AP)",B:B,0)),0) -> 366099831206 | E47: =IFERROR(INDEX(E:E,MATCH("Accounts Receivable (AR)",B:B,0))+INDEX(E:E,MATCH("Inventory — Total",B:B,0))-INDEX(E:E,MATCH("Accounts Payable (AP)",B:B,0)),0) -> 336486428368
B49: D. MEMO LINES (capital expenditure story)
B50: Memo: Long-term investments (MS 250) | C50: =IFERROR(INDEX('01_Inputs'!D:D,MATCH("250",'01_Inputs'!C:C,0)),0) -> 299132386348 | D50: =IFERROR(INDEX('01_Inputs'!E:E,MATCH("250",'01_Inputs'!C:C,0)),0) -> 117453931611 | E50: =IFERROR(INDEX('01_Inputs'!F:F,MATCH("250",'01_Inputs'!C:C,0)),0) -> 58184439385
B51: Memo: LT receivables + construction in progress (MS 210/240) | C51: =IFERROR(INDEX('01_Inputs'!D:D,MATCH("210_240",'01_Inputs'!C:C,0)),0) -> 7266648143 | D51: =IFERROR(INDEX('01_Inputs'!E:E,MATCH("210_240",'01_Inputs'!C:C,0)),0) -> 6621174710 | E51: =IFERROR(INDEX('01_Inputs'!F:F,MATCH("210_240",'01_Inputs'!C:C,0)),0) -> 284677722914
B52: Memo: Advances from customers (MS 313) | C52: =IFERROR(INDEX('01_Inputs'!D:D,MATCH("131_advance",'01_Inputs'!C:C,0)),0) -> 20890314563 | D52: =IFERROR(INDEX('01_Inputs'!E:E,MATCH("131_advance",'01_Inputs'!C:C,0)),0) -> 11074253824 | E52: =IFERROR(INDEX('01_Inputs'!F:F,MATCH("131_advance",'01_Inputs'!C:C,0)),0) -> 35223524344
B53: Memo: Gross fixed assets (MS 211) | C53: =IFERROR(INDEX('01_Inputs'!D:D,MATCH("211",'01_Inputs'!C:C,0)),0) -> 1605315062164 | D53: =IFERROR(INDEX('01_Inputs'!E:E,MATCH("211",'01_Inputs'!C:C,0)),0) -> 1725104912204 | E53: =IFERROR(INDEX('01_Inputs'!F:F,MATCH("211",'01_Inputs'!C:C,0)),0) -> 1876373107976

Sheet 04_Ratios
B2: 04 — FINANCIAL RATIOS + DUPONT
B3: All ratios are linked automatically from 03_FS_Restated. Do not overwrite.
B5: Ratio | C5: FY2023 | D5: FY2024 | E5: FY2025 | F5: Interpretation / Benchmark
A6: A. LIQUIDITY
B7: Current Ratio | C7: =IFERROR((IFERROR(INDEX('03_FS_Restated'!C:C,MATCH("TOTAL CURRENT ASSETS",'03_FS_Restated'!B:B,0)),0))/(IFERROR(INDEX('03_FS_Restated'!C:C,MATCH("TOTAL CURRENT LIABILITIES",'03_FS_Restated'!B:B,0)),0)),0) -> 1.2513381 | D7: =IFERROR((IFERROR(INDEX('03_FS_Restated'!D:D,MATCH("TOTAL CURRENT ASSETS",'03_FS_Restated'!B:B,0)),0))/(IFERROR(INDEX('03_FS_Restated'!D:D,MATCH("TOTAL CURRENT LIABILITIES",'03_FS_Restated'!B:B,0)),0)),0) -> 1.6321814 | E7: =IFERROR((IFERROR(INDEX('03_FS_Restated'!E:E,MATCH("TOTAL CURRENT ASSETS",'03_FS_Restated'!B:B,0)),0))/(IFERROR(INDEX('03_FS_Restated'!E:E,MATCH("TOTAL CURRENT LIABILITIES",'03_FS_Restated'!B:B,0)),0)),0) -> 1.8210941 | F7: Above 1.5 is healthy
B8: Quick Ratio | C8: =IFERROR((IFERROR(INDEX('03_FS_Restated'!C:C,MATCH("TOTAL CURRENT ASSETS",'03_FS_Restated'!B:B,0)),0)-IFERROR(INDEX('03_FS_Restated'!C:C,MATCH("Inventory — Total",'03_FS_Restated'!B:B,0)),0))/(IFERROR(INDEX('03_FS_Restated'!C:C,MATCH("TOTAL CURRENT LIABILITIES",'03_FS_Restated'!B:B,0)),0)),0) -> 0.90526696 | D8: =IFERROR((IFERROR(INDEX('03_FS_Restated'!D:D,MATCH("TOTAL CURRENT ASSETS",'03_FS_Restated'!B:B,0)),0)-IFERROR(INDEX('03_FS_Restated'!D:D,MATCH("Inventory — Total",'03_FS_Restated'!B:B,0)),0))/(IFERROR(INDEX('03_FS_Restated'!D:D,MATCH("TOTAL CURRENT LIABILITIES",'03_FS_Restated'!B:B,0)),0)),0) -> 1.2046844 | E8: =IFERROR((IFERROR(INDEX('03_FS_Restated'!E:E,MATCH("TOTAL CURRENT ASSETS",'03_FS_Restated'!B:B,0)),0)-IFERROR(INDEX('03_FS_Restated'!E:E,MATCH("Inventory — Total",'03_FS_Restated'!B:B,0)),0))/(IFERROR(INDEX('03_FS_Restated'!E:E,MATCH("TOTAL CURRENT LIABILITIES",'03_FS_Restated'!B:B,0)),0)),0) -> 1.4278879 | F8: Above 1.0 is healthy (excludes inventory)
B9: Cash Ratio | C9: =IFERROR((IFERROR(INDEX('03_FS_Restated'!C:C,MATCH("Cash and equivalents",'03_FS_Restated'!B:B,0)),0))/(IFERROR(INDEX('03_FS_Restated'!C:C,MATCH("TOTAL CURRENT LIABILITIES",'03_FS_Restated'!B:B,0)),0)),0) -> 0.10256946 | D9: =IFERROR((IFERROR(INDEX('03_FS_Restated'!D:D,MATCH("Cash and equivalents",'03_FS_Restated'!B:B,0)),0))/(IFERROR(INDEX('03_FS_Restated'!D:D,MATCH("TOTAL CURRENT LIABILITIES",'03_FS_Restated'!B:B,0)),0)),0) -> 0.37512444 | E9: =IFERROR((IFERROR(INDEX('03_FS_Restated'!E:E,MATCH("Cash and equivalents",'03_FS_Restated'!B:B,0)),0))/(IFERROR(INDEX('03_FS_Restated'!E:E,MATCH("TOTAL CURRENT LIABILITIES",'03_FS_Restated'!B:B,0)),0)),0) -> 0.56906603 | F9: Measures immediate liquidity
B10: NWC / Revenue | C10: =IFERROR((IFERROR(INDEX('03_FS_Restated'!C:C,MATCH("Net Working Capital = CA − CL",'03_FS_Restated'!B:B,0)),0))/(IFERROR(INDEX('03_FS_Restated'!C:C,MATCH("Revenue (net)",'03_FS_Restated'!B:B,0)),0)),0) -> 0.082118598 | D10: =IFERROR((IFERROR(INDEX('03_FS_Restated'!D:D,MATCH("Net Working Capital = CA − CL",'03_FS_Restated'!B:B,0)),0))/(IFERROR(INDEX('03_FS_Restated'!D:D,MATCH("Revenue (net)",'03_FS_Restated'!B:B,0)),0)),0) -> 0.15426813 | E10: =IFERROR((IFERROR(INDEX('03_FS_Restated'!E:E,MATCH("Net Working Capital = CA − CL",'03_FS_Restated'!B:B,0)),0))/(IFERROR(INDEX('03_FS_Restated'!E:E,MATCH("Revenue (net)",'03_FS_Restated'!B:B,0)),0)),0) -> 0.21626918 | F10: WC intensity
A12: B. PROFITABILITY
B13: Gross Margin | C13: =IFERROR((IFERROR(INDEX('03_FS_Restated'!C:C,MATCH("Gross Profit",'03_FS_Restated'!B:B,0)),0))/(IFERROR(INDEX('03_FS_Restated'!C:C,MATCH("Revenue (net)",'03_FS_Restated'!B:B,0)),0)),0) -> 0.14839842 | D13: =IFERROR((IFERROR(INDEX('03_FS_Restated'!D:D,MATCH("Gross Profit",'03_FS_Restated'!B:B,0)),0))/(IFERROR(INDEX('03_FS_Restated'!D:D,MATCH("Revenue (net)",'03_FS_Restated'!B:B,0)),0)),0) -> 0.18629574 | E13: =IFERROR((IFERROR(INDEX('03_FS_Restated'!E:E,MATCH("Gross Profit",'03_FS_Restated'!B:B,0)),0))/(IFERROR(INDEX('03_FS_Restated'!E:E,MATCH("Revenue (net)",'03_FS_Restated'!B:B,0)),0)),0) -> 0.17269034 | F13: Vietnamese manufacturing benchmark: approximately 10-20%
B14: Operating Margin (EBIT margin) | C14: =IFERROR((IFERROR(INDEX('03_FS_Restated'!C:C,MATCH("Operating Profit",'03_FS_Restated'!B:B,0)),0))/(IFERROR(INDEX('03_FS_Restated'!C:C,MATCH("Revenue (net)",'03_FS_Restated'!B:B,0)),0)),0) -> 0.057407702 | D14: =IFERROR((IFERROR(INDEX('03_FS_Restated'!D:D,MATCH("Operating Profit",'03_FS_Restated'!B:B,0)),0))/(IFERROR(INDEX('03_FS_Restated'!D:D,MATCH("Revenue (net)",'03_FS_Restated'!B:B,0)),0)),0) -> 0.053578277 | E14: =IFERROR((IFERROR(INDEX('03_FS_Restated'!E:E,MATCH("Operating Profit",'03_FS_Restated'!B:B,0)),0))/(IFERROR(INDEX('03_FS_Restated'!E:E,MATCH("Revenue (net)",'03_FS_Restated'!B:B,0)),0)),0) -> 0.069665155
B15: EBITDA Margin | C15: =IFERROR((IFERROR(INDEX('03_FS_Restated'!C:C,MATCH("EBITDA",'03_FS_Restated'!B:B,0)),0))/(IFERROR(INDEX('03_FS_Restated'!C:C,MATCH("Revenue (net)",'03_FS_Restated'!B:B,0)),0)),0) -> 0.11172699 | D15: =IFERROR((IFERROR(INDEX('03_FS_Restated'!D:D,MATCH("EBITDA",'03_FS_Restated'!B:B,0)),0))/(IFERROR(INDEX('03_FS_Restated'!D:D,MATCH("Revenue (net)",'03_FS_Restated'!B:B,0)),0)),0) -> 0.10489943 | E15: =IFERROR((IFERROR(INDEX('03_FS_Restated'!E:E,MATCH("EBITDA",'03_FS_Restated'!B:B,0)),0))/(IFERROR(INDEX('03_FS_Restated'!E:E,MATCH("Revenue (net)",'03_FS_Restated'!B:B,0)),0)),0) -> 0.11981719
B16: Net Margin | C16: =IFERROR((IFERROR(INDEX('03_FS_Restated'!C:C,MATCH("Net Income",'03_FS_Restated'!B:B,0)),0))/(IFERROR(INDEX('03_FS_Restated'!C:C,MATCH("Revenue (net)",'03_FS_Restated'!B:B,0)),0)),0) -> 0.047194612 | D16: =IFERROR((IFERROR(INDEX('03_FS_Restated'!D:D,MATCH("Net Income",'03_FS_Restated'!B:B,0)),0))/(IFERROR(INDEX('03_FS_Restated'!D:D,MATCH("Revenue (net)",'03_FS_Restated'!B:B,0)),0)),0) -> 0.041897313 | E16: =IFERROR((IFERROR(INDEX('03_FS_Restated'!E:E,MATCH("Net Income",'03_FS_Restated'!B:B,0)),0))/(IFERROR(INDEX('03_FS_Restated'!E:E,MATCH("Revenue (net)",'03_FS_Restated'!B:B,0)),0)),0) -> 0.051759957
B17: ROA | C17: =IFERROR((IFERROR(INDEX('03_FS_Restated'!C:C,MATCH("Net Income",'03_FS_Restated'!B:B,0)),0))/(IFERROR(INDEX('03_FS_Restated'!C:C,MATCH("TOTAL ASSETS",'03_FS_Restated'!B:B,0)),0)),0) -> 0.046345888 | D17: =IFERROR((IFERROR(INDEX('03_FS_Restated'!D:D,MATCH("Net Income",'03_FS_Restated'!B:B,0)),0))/((INDEX('03_FS_Restated'!D:D,MATCH("TOTAL ASSETS",'03_FS_Restated'!B:B,0))+INDEX('03_FS_Restated'!C:C,MATCH("TOTAL ASSETS",'03_FS_Restated'!B:B,0)))/2),0) -> 0.043852135 | E17: =IFERROR((IFERROR(INDEX('03_FS_Restated'!E:E,MATCH("Net Income",'03_FS_Restated'!B:B,0)),0))/((INDEX('03_FS_Restated'!E:E,MATCH("TOTAL ASSETS",'03_FS_Restated'!B:B,0))+INDEX('03_FS_Restated'!D:D,MATCH("TOTAL ASSETS",'03_FS_Restated'!B:B,0)))/2),0) -> 0.053651624
B18: ROE | C18: =IFERROR((IFERROR(INDEX('03_FS_Restated'!C:C,MATCH("Net Income",'03_FS_Restated'!B:B,0)),0))/(IFERROR(INDEX('03_FS_Restated'!C:C,MATCH("TOTAL EQUITY",'03_FS_Restated'!B:B,0)),0)),0) -> 0.070085928 | D18: =IFERROR((IFERROR(INDEX('03_FS_Restated'!D:D,MATCH("Net Income",'03_FS_Restated'!B:B,0)),0))/((INDEX('03_FS_Restated'!D:D,MATCH("TOTAL EQUITY",'03_FS_Restated'!B:B,0))+INDEX('03_FS_Restated'!C:C,MATCH("TOTAL EQUITY",'03_FS_Restated'!B:B,0)))/2),0) -> 0.064367994 | E18: =IFERROR((IFERROR(INDEX('03_FS_Restated'!E:E,MATCH("Net Income",'03_FS_Restated'!B:B,0)),0))/((INDEX('03_FS_Restated'!E:E,MATCH("TOTAL EQUITY",'03_FS_Restated'!B:B,0))+INDEX('03_FS_Restated'!D:D,MATCH("TOTAL EQUITY",'03_FS_Restated'!B:B,0)))/2),0) -> 0.075186856
B19: ROIC | C19: =IFERROR((IFERROR(INDEX('03_FS_Restated'!C:C,MATCH("Operating Profit",'03_FS_Restated'!B:B,0)),0))*(1-INDEX('02_Assumptions'!C:C,MATCH("Tax rate for NOPAT (ROIC)",'02_Assumptions'!B:B,0)))/(((IFERROR(INDEX('03_FS_Restated'!C:C,MATCH("Short-term debt",'03_FS_Restated'!B:B,0)),0)+IFERROR(INDEX('03_FS_Restated'!C:C,MATCH("Long-term debt",'03_FS_Restated'!B:B,0)),0)))+(IFERROR(INDEX('03_FS_Restated'!C:C,MATCH("TOTAL EQUITY",'03_FS_Restated'!B:B,0)),0))),0) -> 0.050380211 | D19: =IFERROR((IFERROR(INDEX('03_FS_Restated'!D:D,MATCH("Operating Profit",'03_FS_Restated'!B:B,0)),0))*(1-INDEX('02_Assumptions'!C:C,MATCH("Tax rate for NOPAT (ROIC)",'02_Assumptions'!B:B,0)))/((((INDEX('03_FS_Restated'!D:D,MATCH("Short-term debt",'03_FS_Restated'!B:B,0))+INDEX('03_FS_Restated'!C:C,MATCH("Short-term debt",'03_FS_Restated'!B:B,0)))/2+(INDEX('03_FS_Restated'!D:D,MATCH("Long-term debt",'03_FS_Restated'!B:B,0))+INDEX('03_FS_Restated'!C:C,MATCH("Long-term debt",'03_FS_Restated'!B:B,0)))/2))+((INDEX('03_FS_Restated'!D:D,MATCH("TOTAL EQUITY",'03_FS_Restated'!B:B,0))+INDEX('03_FS_Restated'!C:C,MATCH("TOTAL EQUITY",'03_FS_Restated'!B:B,0)))/2)),0) -> 0.051031476 | E19: =IFERROR((IFERROR(INDEX('03_FS_Restated'!E:E,MATCH("Operating Profit",'03_FS_Restated'!B:B,0)),0))*(1-INDEX('02_Assumptions'!C:C,MATCH("Tax rate for NOPAT (ROIC)",'02_Assumptions'!B:B,0)))/((((INDEX('03_FS_Restated'!E:E,MATCH("Short-term debt",'03_FS_Restated'!B:B,0))+INDEX('03_FS_Restated'!D:D,MATCH("Short-term debt",'03_FS_Restated'!B:B,0)))/2+(INDEX('03_FS_Restated'!E:E,MATCH("Long-term debt",'03_FS_Restated'!B:B,0))+INDEX('03_FS_Restated'!D:D,MATCH("Long-term debt",'03_FS_Restated'!B:B,0)))/2))+((INDEX('03_FS_Restated'!E:E,MATCH("TOTAL EQUITY",'03_FS_Restated'!B:B,0))+INDEX('03_FS_Restated'!D:D,MATCH("TOTAL EQUITY",'03_FS_Restated'!B:B,0)))/2)),0) -> 0.067453657 | F19: NOPAT / (Debt + Equity). Tax rate is a driver on 02_Assumptions, not hardcoded.
A21: C. EFFICIENCY (Turnover)
B22: Asset Turnover | C22: =IFERROR((IFERROR(INDEX('03_FS_Restated'!C:C,MATCH("Revenue (net)",'03_FS_Restated'!B:B,0)),0))/(IFERROR(INDEX('03_FS_Restated'!C:C,MATCH("TOTAL ASSETS",'03_FS_Restated'!B:B,0)),0)),0) -> 0.9820165 | D22: =IFERROR((IFERROR(INDEX('03_FS_Restated'!D:D,MATCH("Revenue (net)",'03_FS_Restated'!B:B,0)),0))/((INDEX('03_FS_Restated'!D:D,MATCH("TOTAL ASSETS",'03_FS_Restated'!B:B,0))+INDEX('03_FS_Restated'!C:C,MATCH("TOTAL ASSETS",'03_FS_Restated'!B:B,0)))/2),0) -> 1.0466575 | E22: =IFERROR((IFERROR(INDEX('03_FS_Restated'!E:E,MATCH("Revenue (net)",'03_FS_Restated'!B:B,0)),0))/((INDEX('03_FS_Restated'!E:E,MATCH("TOTAL ASSETS",'03_FS_Restated'!B:B,0))+INDEX('03_FS_Restated'!D:D,MATCH("TOTAL ASSETS",'03_FS_Restated'!B:B,0)))/2),0) -> 1.0365469
B23: Fixed Asset Turnover | C23: =IFERROR((IFERROR(INDEX('03_FS_Restated'!C:C,MATCH("Revenue (net)",'03_FS_Restated'!B:B,0)),0))/(IFERROR(INDEX('03_FS_Restated'!C:C,MATCH("Fixed Assets — Net",'03_FS_Restated'!B:B,0)),0)),0) -> 2.5531522 | D23: =IFERROR((IFERROR(INDEX('03_FS_Restated'!D:D,MATCH("Revenue (net)",'03_FS_Restated'!B:B,0)),0))/((INDEX('03_FS_Restated'!D:D,MATCH("Fixed Assets — Net",'03_FS_Restated'!B:B,0))+INDEX('03_FS_Restated'!C:C,MATCH("Fixed Assets — Net",'03_FS_Restated'!B:B,0)))/2),0) -> 2.5766384 | E23: =IFERROR((IFERROR(INDEX('03_FS_Restated'!E:E,MATCH("Revenue (net)",'03_FS_Restated'!B:B,0)),0))/((INDEX('03_FS_Restated'!E:E,MATCH("Fixed Assets — Net",'03_FS_Restated'!B:B,0))+INDEX('03_FS_Restated'!D:D,MATCH("Fixed Assets — Net",'03_FS_Restated'!B:B,0)))/2),0) -> 2.688563
B24: Inventory Turnover | C24: =IFERROR((IFERROR(INDEX('03_FS_Restated'!C:C,MATCH("COGS",'03_FS_Restated'!B:B,0)),0))/(IFERROR(INDEX('03_FS_Restated'!C:C,MATCH("Inventory — Total",'03_FS_Restated'!B:B,0)),0)),0) -> 7.531611 | D24: =IFERROR((IFERROR(INDEX('03_FS_Restated'!D:D,MATCH("COGS",'03_FS_Restated'!B:B,0)),0))/((INDEX('03_FS_Restated'!D:D,MATCH("Inventory — Total",'03_FS_Restated'!B:B,0))+INDEX('03_FS_Restated'!C:C,MATCH("Inventory — Total",'03_FS_Restated'!B:B,0)))/2),0) -> 7.5946604 | E24: =IFERROR((IFERROR(INDEX('03_FS_Restated'!E:E,MATCH("COGS",'03_FS_Restated'!B:B,0)),0))/((INDEX('03_FS_Restated'!E:E,MATCH("Inventory — Total",'03_FS_Restated'!B:B,0))+INDEX('03_FS_Restated'!D:D,MATCH("Inventory — Total",'03_FS_Restated'!B:B,0)))/2),0) -> 8.3476243
B25: Receivables Turnover | C25: =IFERROR((IFERROR(INDEX('03_FS_Restated'!C:C,MATCH("Revenue (net)",'03_FS_Restated'!B:B,0)),0))/(IFERROR(INDEX('03_FS_Restated'!C:C,MATCH("Accounts Receivable (AR)",'03_FS_Restated'!B:B,0)),0)),0) -> 9.0354211 | D25: =IFERROR((IFERROR(INDEX('03_FS_Restated'!D:D,MATCH("Revenue (net)",'03_FS_Restated'!B:B,0)),0))/((INDEX('03_FS_Restated'!D:D,MATCH("Accounts Receivable (AR)",'03_FS_Restated'!B:B,0))+INDEX('03_FS_Restated'!C:C,MATCH("Accounts Receivable (AR)",'03_FS_Restated'!B:B,0)))/2),0) -> 7.9950249 | E25: =IFERROR((IFERROR(INDEX('03_FS_Restated'!E:E,MATCH("Revenue (net)",'03_FS_Restated'!B:B,0)),0))/((INDEX('03_FS_Restated'!E:E,MATCH("Accounts Receivable (AR)",'03_FS_Restated'!B:B,0))+INDEX('03_FS_Restated'!D:D,MATCH("Accounts Receivable (AR)",'03_FS_Restated'!B:B,0)))/2),0) -> 7.9711123
B26: Payables Turnover | C26: =IFERROR((IFERROR(INDEX('03_FS_Restated'!C:C,MATCH("COGS",'03_FS_Restated'!B:B,0)),0))/(IFERROR(INDEX('03_FS_Restated'!C:C,MATCH("Accounts Payable (AP)",'03_FS_Restated'!B:B,0)),0)),0) -> 13.732787 | D26: =IFERROR((IFERROR(INDEX('03_FS_Restated'!D:D,MATCH("COGS",'03_FS_Restated'!B:B,0)),0))/((INDEX('03_FS_Restated'!D:D,MATCH("Accounts Payable (AP)",'03_FS_Restated'!B:B,0))+INDEX('03_FS_Restated'!C:C,MATCH("Accounts Payable (AP)",'03_FS_Restated'!B:B,0)))/2),0) -> 12.276861 | E26: =IFERROR((IFERROR(INDEX('03_FS_Restated'!E:E,MATCH("COGS",'03_FS_Restated'!B:B,0)),0))/((INDEX('03_FS_Restated'!E:E,MATCH("Accounts Payable (AP)",'03_FS_Restated'!B:B,0))+INDEX('03_FS_Restated'!D:D,MATCH("Accounts Payable (AP)",'03_FS_Restated'!B:B,0)))/2),0) -> 11.401018
A28: D. LEVERAGE / SOLVENCY
B29: Debt / Assets | C29: =IFERROR(((IFERROR(INDEX('03_FS_Restated'!C:C,MATCH("Short-term debt",'03_FS_Restated'!B:B,0)),0)+IFERROR(INDEX('03_FS_Restated'!C:C,MATCH("Long-term debt",'03_FS_Restated'!B:B,0)),0)))/(IFERROR(INDEX('03_FS_Restated'!C:C,MATCH("TOTAL ASSETS",'03_FS_Restated'!B:B,0)),0)),0) -> 0.23392532 | D29: =IFERROR(((IFERROR(INDEX('03_FS_Restated'!D:D,MATCH("Short-term debt",'03_FS_Restated'!B:B,0)),0)+IFERROR(INDEX('03_FS_Restated'!D:D,MATCH("Long-term debt",'03_FS_Restated'!B:B,0)),0)))/(IFERROR(INDEX('03_FS_Restated'!D:D,MATCH("TOTAL ASSETS",'03_FS_Restated'!B:B,0)),0)),0) -> 0.15902111 | E29: =IFERROR(((IFERROR(INDEX('03_FS_Restated'!E:E,MATCH("Short-term debt",'03_FS_Restated'!B:B,0)),0)+IFERROR(INDEX('03_FS_Restated'!E:E,MATCH("Long-term debt",'03_FS_Restated'!B:B,0)),0)))/(IFERROR(INDEX('03_FS_Restated'!E:E,MATCH("TOTAL ASSETS",'03_FS_Restated'!B:B,0)),0)),0) -> 0.13050378
B30: Debt / Equity | C30: =IFERROR(((IFERROR(INDEX('03_FS_Restated'!C:C,MATCH("Short-term debt",'03_FS_Restated'!B:B,0)),0)+IFERROR(INDEX('03_FS_Restated'!C:C,MATCH("Long-term debt",'03_FS_Restated'!B:B,0)),0)))/(IFERROR(INDEX('03_FS_Restated'!C:C,MATCH("TOTAL EQUITY",'03_FS_Restated'!B:B,0)),0)),0) -> 0.35375033 | D30: =IFERROR(((IFERROR(INDEX('03_FS_Restated'!D:D,MATCH("Short-term debt",'03_FS_Restated'!B:B,0)),0)+IFERROR(INDEX('03_FS_Restated'!D:D,MATCH("Long-term debt",'03_FS_Restated'!B:B,0)),0)))/(IFERROR(INDEX('03_FS_Restated'!D:D,MATCH("TOTAL EQUITY",'03_FS_Restated'!B:B,0)),0)),0) -> 0.22627141 | E30: =IFERROR(((IFERROR(INDEX('03_FS_Restated'!E:E,MATCH("Short-term debt",'03_FS_Restated'!B:B,0)),0)+IFERROR(INDEX('03_FS_Restated'!E:E,MATCH("Long-term debt",'03_FS_Restated'!B:B,0)),0)))/(IFERROR(INDEX('03_FS_Restated'!E:E,MATCH("TOTAL EQUITY",'03_FS_Restated'!B:B,0)),0)),0) -> 0.18080065
B31: Equity Multiplier | C31: =IFERROR((IFERROR(INDEX('03_FS_Restated'!C:C,MATCH("TOTAL ASSETS",'03_FS_Restated'!B:B,0)),0))/(IFERROR(INDEX('03_FS_Restated'!C:C,MATCH("TOTAL EQUITY",'03_FS_Restated'!B:B,0)),0)),0) -> 1.5122362 | D31: =IFERROR((IFERROR(INDEX('03_FS_Restated'!D:D,MATCH("TOTAL ASSETS",'03_FS_Restated'!B:B,0)),0))/(IFERROR(INDEX('03_FS_Restated'!D:D,MATCH("TOTAL EQUITY",'03_FS_Restated'!B:B,0)),0)),0) -> 1.4229017 | E31: =IFERROR((IFERROR(INDEX('03_FS_Restated'!E:E,MATCH("TOTAL ASSETS",'03_FS_Restated'!B:B,0)),0))/(IFERROR(INDEX('03_FS_Restated'!E:E,MATCH("TOTAL EQUITY",'03_FS_Restated'!B:B,0)),0)),0) -> 1.3854055
B32: Interest Coverage | C32: =IFERROR((IFERROR(INDEX('03_FS_Restated'!C:C,MATCH("Operating Profit",'03_FS_Restated'!B:B,0)),0))/(IFERROR(INDEX('03_FS_Restated'!C:C,MATCH(" o/w Interest expense",'03_FS_Restated'!B:B,0)),0)),0) -> 2.548209 | D32: =IFERROR((IFERROR(INDEX('03_FS_Restated'!D:D,MATCH("Operating Profit",'03_FS_Restated'!B:B,0)),0))/(IFERROR(INDEX('03_FS_Restated'!D:D,MATCH(" o/w Interest expense",'03_FS_Restated'!B:B,0)),0)),0) -> 5.2985678 | E32: =IFERROR((IFERROR(INDEX('03_FS_Restated'!E:E,MATCH("Operating Profit",'03_FS_Restated'!B:B,0)),0))/(IFERROR(INDEX('03_FS_Restated'!E:E,MATCH(" o/w Interest expense",'03_FS_Restated'!B:B,0)),0)),0) -> 10.000404
A34: E. DUPONT DECOMPOSITION
B35: ROE = Net Margin × Asset Turnover × Equity Multiplier
B36: (1) Net Margin | C36: =IFERROR((IFERROR(INDEX('03_FS_Restated'!C:C,MATCH("Net Income",'03_FS_Restated'!B:B,0)),0))/(IFERROR(INDEX('03_FS_Restated'!C:C,MATCH("Revenue (net)",'03_FS_Restated'!B:B,0)),0)),0) -> 0.047194612 | D36: =IFERROR((IFERROR(INDEX('03_FS_Restated'!D:D,MATCH("Net Income",'03_FS_Restated'!B:B,0)),0))/(IFERROR(INDEX('03_FS_Restated'!D:D,MATCH("Revenue (net)",'03_FS_Restated'!B:B,0)),0)),0) -> 0.041897313 | E36: =IFERROR((IFERROR(INDEX('03_FS_Restated'!E:E,MATCH("Net Income",'03_FS_Restated'!B:B,0)),0))/(IFERROR(INDEX('03_FS_Restated'!E:E,MATCH("Revenue (net)",'03_FS_Restated'!B:B,0)),0)),0) -> 0.051759957
B37: (2) Asset Turnover | C37: =IFERROR((IFERROR(INDEX('03_FS_Restated'!C:C,MATCH("Revenue (net)",'03_FS_Restated'!B:B,0)),0))/(IFERROR(INDEX('03_FS_Restated'!C:C,MATCH("TOTAL ASSETS",'03_FS_Restated'!B:B,0)),0)),0) -> 0.9820165 | D37: =IFERROR((IFERROR(INDEX('03_FS_Restated'!D:D,MATCH("Revenue (net)",'03_FS_Restated'!B:B,0)),0))/((INDEX('03_FS_Restated'!D:D,MATCH("TOTAL ASSETS",'03_FS_Restated'!B:B,0))+INDEX('03_FS_Restated'!C:C,MATCH("TOTAL ASSETS",'03_FS_Restated'!B:B,0)))/2),0) -> 1.0466575 | E37: =IFERROR((IFERROR(INDEX('03_FS_Restated'!E:E,MATCH("Revenue (net)",'03_FS_Restated'!B:B,0)),0))/((INDEX('03_FS_Restated'!E:E,MATCH("TOTAL ASSETS",'03_FS_Restated'!B:B,0))+INDEX('03_FS_Restated'!D:D,MATCH("TOTAL ASSETS",'03_FS_Restated'!B:B,0)))/2),0) -> 1.0365469
B38: (3) Equity Multiplier | C38: =IFERROR((IFERROR(INDEX('03_FS_Restated'!C:C,MATCH("TOTAL ASSETS",'03_FS_Restated'!B:B,0)),0))/(IFERROR(INDEX('03_FS_Restated'!C:C,MATCH("TOTAL EQUITY",'03_FS_Restated'!B:B,0)),0)),0) -> 1.5122362 | D38: =IFERROR(((INDEX('03_FS_Restated'!D:D,MATCH("TOTAL ASSETS",'03_FS_Restated'!B:B,0))+INDEX('03_FS_Restated'!C:C,MATCH("TOTAL ASSETS",'03_FS_Restated'!B:B,0)))/2)/((INDEX('03_FS_Restated'!D:D,MATCH("TOTAL EQUITY",'03_FS_Restated'!B:B,0))+INDEX('03_FS_Restated'!C:C,MATCH("TOTAL EQUITY",'03_FS_Restated'!B:B,0)))/2),0) -> 1.4678418 | E38: =IFERROR(((INDEX('03_FS_Restated'!E:E,MATCH("TOTAL ASSETS",'03_FS_Restated'!B:B,0))+INDEX('03_FS_Restated'!D:D,MATCH("TOTAL ASSETS",'03_FS_Restated'!B:B,0)))/2)/((INDEX('03_FS_Restated'!E:E,MATCH("TOTAL EQUITY",'03_FS_Restated'!B:B,0))+INDEX('03_FS_Restated'!D:D,MATCH("TOTAL EQUITY",'03_FS_Restated'!B:B,0)))/2),0) -> 1.4013901
B39: ROE (product) | C39: =C36*C37*C38 -> 0.070085928 | D39: =D36*D37*D38 -> 0.064367994 | E39: =E36*E37*E38 -> 0.075186856
B40: ROE (direct check) | C40: =IFERROR((IFERROR(INDEX('03_FS_Restated'!C:C,MATCH("Net Income",'03_FS_Restated'!B:B,0)),0))/(IFERROR(INDEX('03_FS_Restated'!C:C,MATCH("TOTAL EQUITY",'03_FS_Restated'!B:B,0)),0)),0) -> 0.070085928 | D40: =IFERROR((IFERROR(INDEX('03_FS_Restated'!D:D,MATCH("Net Income",'03_FS_Restated'!B:B,0)),0))/((INDEX('03_FS_Restated'!D:D,MATCH("TOTAL EQUITY",'03_FS_Restated'!B:B,0))+INDEX('03_FS_Restated'!C:C,MATCH("TOTAL EQUITY",'03_FS_Restated'!B:B,0)))/2),0) -> 0.064367994 | E40: =IFERROR((IFERROR(INDEX('03_FS_Restated'!E:E,MATCH("Net Income",'03_FS_Restated'!B:B,0)),0))/((INDEX('03_FS_Restated'!E:E,MATCH("TOTAL EQUITY",'03_FS_Restated'!B:B,0))+INDEX('03_FS_Restated'!D:D,MATCH("TOTAL EQUITY",'03_FS_Restated'!B:B,0)))/2),0) -> 0.075186856
B42: F. COST OF DEBT & TAX
B43: Metric | C43: FY2023 | D43: FY2024 | E43: FY2025 | F43: Note
B44: Gross debt (ST + LT) | C44: =INDEX('03_FS_Restated'!C:C,MATCH("Short-term debt",'03_FS_Restated'!B:B,0))+INDEX('03_FS_Restated'!C:C,MATCH("Long-term debt",'03_FS_Restated'!B:B,0)) -> 485776292665 | D44: =INDEX('03_FS_Restated'!D:D,MATCH("Short-term debt",'03_FS_Restated'!B:B,0))+INDEX('03_FS_Restated'!D:D,MATCH("Long-term debt",'03_FS_Restated'!B:B,0)) -> 306947495421 | E44: =INDEX('03_FS_Restated'!E:E,MATCH("Short-term debt",'03_FS_Restated'!B:B,0))+INDEX('03_FS_Restated'!E:E,MATCH("Long-term debt",'03_FS_Restated'!B:B,0)) -> 330070184566
B45: Average gross debt | C45: =C44 -> 485776292665 | D45: =(D44+C44)/2 -> 396361894043 | E45: =(E44+D44)/2 -> 3.1850884e+11
B46: Implied cost of debt | C46: =IFERROR(INDEX('03_FS_Restated'!C:C,MATCH(" o/w Interest expense",'03_FS_Restated'!B:B,0))/C45,0) -> 0.094575069 | D46: =IFERROR(INDEX('03_FS_Restated'!D:D,MATCH(" o/w Interest expense",'03_FS_Restated'!B:B,0))/D45,0) -> 0.053495494 | E46: =IFERROR(INDEX('03_FS_Restated'!E:E,MATCH(" o/w Interest expense",'03_FS_Restated'!B:B,0))/E45,0) -> 0.050549287
B47: Effective tax rate | C47: =IFERROR(INDEX('03_FS_Restated'!C:C,MATCH("Tax expense",'03_FS_Restated'!B:B,0))/INDEX('03_FS_Restated'!C:C,MATCH("EBT",'03_FS_Restated'!B:B,0)),0) -> 0.20158732 | D47: =IFERROR(INDEX('03_FS_Restated'!D:D,MATCH("Tax expense",'03_FS_Restated'!B:B,0))/INDEX('03_FS_Restated'!D:D,MATCH("EBT",'03_FS_Restated'!B:B,0)),0) -> 0.2118572 | E47: =IFERROR(INDEX('03_FS_Restated'!E:E,MATCH("Tax expense",'03_FS_Restated'!B:B,0))/INDEX('03_FS_Restated'!E:E,MATCH("EBT",'03_FS_Restated'!B:B,0)),0) -> 0.26102648

Sheet 05_CCC
B2: 05 — CASH CONVERSION CYCLE (CCC)
B5: Metric | C5: FY2023 | D5: FY2024 | E5: FY2025 | F5: Note
A6: A. INPUT - average balances (from 03_FS_Restated)
B7: Revenue (net) | C7: =IFERROR(IFERROR(INDEX('03_FS_Restated'!C:C,MATCH("Revenue (net)",'03_FS_Restated'!B:B,0)),0),0) -> 2039284758153 | D7: =IFERROR(IFERROR(INDEX('03_FS_Restated'!D:D,MATCH("Revenue (net)",'03_FS_Restated'!B:B,0)),0),0) -> 2096905452640 | E7: =IFERROR(IFERROR(INDEX('03_FS_Restated'!E:E,MATCH("Revenue (net)",'03_FS_Restated'!B:B,0)),0),0) -> 2311204952919
B8: COGS | C8: =IFERROR(IFERROR(INDEX('03_FS_Restated'!C:C,MATCH("COGS",'03_FS_Restated'!B:B,0)),0),0) -> 1736658116472 | D8: =IFERROR(IFERROR(INDEX('03_FS_Restated'!D:D,MATCH("COGS",'03_FS_Restated'!B:B,0)),0),0) -> 1706260890180 | E8: =IFERROR(IFERROR(INDEX('03_FS_Restated'!E:E,MATCH("COGS",'03_FS_Restated'!B:B,0)),0),0) -> 1912082184770
B9: Days in period | C9: =IFERROR(INDEX('02_Assumptions'!C:C,MATCH("Days per year",'02_Assumptions'!B:B,0)),365) -> 365 | D9: =IFERROR(INDEX('02_Assumptions'!C:C,MATCH("Days per year",'02_Assumptions'!B:B,0)),365) -> 365 | E9: =IFERROR(INDEX('02_Assumptions'!C:C,MATCH("Days per year",'02_Assumptions'!B:B,0)),365) -> 365
B10: Trade receivables - average | C10: =IFERROR((INDEX('03_FS_Restated'!C:C,MATCH("Accounts Receivable (AR)",'03_FS_Restated'!B:B,0))+C41)/2,0) -> 288150748852 | D10: =IFERROR((INDEX('03_FS_Restated'!D:D,MATCH("Accounts Receivable (AR)",'03_FS_Restated'!B:B,0))+INDEX('03_FS_Restated'!C:C,MATCH("Accounts Receivable (AR)",'03_FS_Restated'!B:B,0)))/2,0) -> 262276288798 | E10: =IFERROR((INDEX('03_FS_Restated'!E:E,MATCH("Accounts Receivable (AR)",'03_FS_Restated'!B:B,0))+INDEX('03_FS_Restated'!D:D,MATCH("Accounts Receivable (AR)",'03_FS_Restated'!B:B,0)))/2,0) -> 289947608931
B11: Inventory, raw materials - average | C11: =IFERROR(IFERROR(INDEX('03_FS_Restated'!C:C,MATCH("Inventory — Raw Material (NVL)",'03_FS_Restated'!B:B,0)),0),0) -> 110619487264 | D11: =IFERROR((INDEX('03_FS_Restated'!D:D,MATCH("Inventory — Raw Material (NVL)",'03_FS_Restated'!B:B,0))+INDEX('03_FS_Restated'!C:C,MATCH("Inventory — Raw Material (NVL)",'03_FS_Restated'!B:B,0)))/2,0) -> 110118508542 | E11: =IFERROR((INDEX('03_FS_Restated'!E:E,MATCH("Inventory — Raw Material (NVL)",'03_FS_Restated'!B:B,0))+INDEX('03_FS_Restated'!D:D,MATCH("Inventory — Raw Material (NVL)",'03_FS_Restated'!B:B,0)))/2,0) -> 1.093797e+11
B12: Inventory, work in progress - average | C12: =IFERROR(IFERROR(INDEX('03_FS_Restated'!C:C,MATCH("Inventory — Work in Progress (WIP)",'03_FS_Restated'!B:B,0)),0),0) -> 49989085832 | D12: =IFERROR((INDEX('03_FS_Restated'!D:D,MATCH("Inventory — Work in Progress (WIP)",'03_FS_Restated'!B:B,0))+INDEX('03_FS_Restated'!C:C,MATCH("Inventory — Work in Progress (WIP)",'03_FS_Restated'!B:B,0)))/2,0) -> 48245267791 | E12: =IFERROR((INDEX('03_FS_Restated'!E:E,MATCH("Inventory — Work in Progress (WIP)",'03_FS_Restated'!B:B,0))+INDEX('03_FS_Restated'!D:D,MATCH("Inventory — Work in Progress (WIP)",'03_FS_Restated'!B:B,0)))/2,0) -> 50962307686
B13: Inventory, finished goods - average | C13: =IFERROR(IFERROR(INDEX('03_FS_Restated'!C:C,MATCH("Inventory — Finished Goods (FG)",'03_FS_Restated'!B:B,0)),0),0) -> 60251021462 | D13: =IFERROR((INDEX('03_FS_Restated'!D:D,MATCH("Inventory — Finished Goods (FG)",'03_FS_Restated'!B:B,0))+INDEX('03_FS_Restated'!C:C,MATCH("Inventory — Finished Goods (FG)",'03_FS_Restated'!B:B,0)))/2,0) -> 54832032143 | E13: =IFERROR((INDEX('03_FS_Restated'!E:E,MATCH("Inventory — Finished Goods (FG)",'03_FS_Restated'!B:B,0))+INDEX('03_FS_Restated'!D:D,MATCH("Inventory — Finished Goods (FG)",'03_FS_Restated'!B:B,0)))/2,0) -> 53931634372
B14: Inventory, total - average | C14: =IFERROR((INDEX('03_FS_Restated'!C:C,MATCH("Inventory — Total",'03_FS_Restated'!B:B,0))+C42)/2,0) -> 298588965802 | D14: =IFERROR((INDEX('03_FS_Restated'!D:D,MATCH("Inventory — Total",'03_FS_Restated'!B:B,0))+INDEX('03_FS_Restated'!C:C,MATCH("Inventory — Total",'03_FS_Restated'!B:B,0)))/2,0) -> 224665857300 | E14: =IFERROR((INDEX('03_FS_Restated'!E:E,MATCH("Inventory — Total",'03_FS_Restated'!B:B,0))+INDEX('03_FS_Restated'!D:D,MATCH("Inventory — Total",'03_FS_Restated'!B:B,0)))/2,0) -> 2.2905705e+11
B15: Trade payables - average | C15: =IFERROR((INDEX('03_FS_Restated'!C:C,MATCH("Accounts Payable (AP)",'03_FS_Restated'!B:B,0))+C43)/2,0) -> 2.0207913e+11 | D15: =IFERROR((INDEX('03_FS_Restated'!D:D,MATCH("Accounts Payable (AP)",'03_FS_Restated'!B:B,0))+INDEX('03_FS_Restated'!C:C,MATCH("Accounts Payable (AP)",'03_FS_Restated'!B:B,0)))/2,0) -> 1.3898185e+11 | E15: =IFERROR((INDEX('03_FS_Restated'!E:E,MATCH("Accounts Payable (AP)",'03_FS_Restated'!B:B,0))+INDEX('03_FS_Restated'!D:D,MATCH("Accounts Payable (AP)",'03_FS_Restated'!B:B,0)))/2,0) -> 1.6771153e+11
A17: B. CCC DECOMPOSITION
B18: DSO — Days Sales Outstanding | C18: =IFERROR(C10/C7*C9,0) -> 51.574466 | D18: =IFERROR(D10/D7*D9,0) -> 45.653391 | E18: =IFERROR(E10/E7*E9,0) -> 45.790347
B19: DIO — NVL | C19: =IFERROR(C11/C8*C9,0) -> 23.249316 | D19: =IFERROR(D11/D8*D9,0) -> 23.556336 | E19: =IFERROR(E11/E8*E9,0) -> 20.879641
B20: DIO — WIP | C20: =IFERROR(C12/C8*C9,0) -> 10.506395 | D20: =IFERROR(D12/D8*D9,0) -> 10.320534 | E20: =IFERROR(E12/E8*E9,0) -> 9.7282651
B21: DIO — FG | C21: =IFERROR(C13/C8*C9,0) -> 12.663185 | D21: =IFERROR(D13/D8*D9,0) -> 11.729561 | E21: =IFERROR(E13/E8*E9,0) -> 10.295084
B22: DIO — Total | C22: =IFERROR(C14/C8*C9,0) -> 62.755571 | D22: =IFERROR(D14/D8*D9,0) -> 48.060082 | E22: =IFERROR(E14/E8*E9,0) -> 43.725015
B23: DPO — Days Payable Outstanding | C23: =IFERROR(C15/C8*C9,0) -> 42.471734 | D23: =IFERROR(D15/D8*D9,0) -> 29.730726 | E23: =IFERROR(E15/E8*E9,0) -> 32.014685
B24: CCC = DSO + DIO(Total) − DPO | C24: =C18+C22-C23 -> 71.858304 | D24: =D18+D22-D23 -> 63.982747 | E24: =E18+E22-E23 -> 57.500678
A26: C. CONVERSION TO VND - capital tied up and sensitivity
B27: One day of CCC in VND = Revenue / 365 | C27: =IFERROR(C7/C9,0) -> 5.5870815e+09 | D27: =IFERROR(D7/D9,0) -> 5.7449464e+09 | E27: =IFERROR(E7/E9,0) -> 6.3320684e+09
B28: Working capital tied up = CCC x VND/day | C28: =C24*C27 -> 4.014782e+11 | D28: =D24*D27 -> 3.6757745e+11 | E28: =E24*E27 -> 3.6409822e+11
A30: D. SENSITIVITY: change in CCC to VND (latest financial year)
B31: Change in CCC (days) | C31: VND released (+) / additional capital tied up (-) | F31: Note
B32: -15 days (best case) | C32: =INDEX('02_Assumptions'!C:C,MATCH("∆CCC scenario 3 (days)",'02_Assumptions'!B:B,0)) -> -15 | D32: =-C32*E27 -> 9.4981025e+10 | F32: Aggressive
B33: -10 days | C33: =INDEX('02_Assumptions'!C:C,MATCH("∆CCC scenario 2 (days)",'02_Assumptions'!B:B,0)) -> -10 | D33: =-C33*E27 -> 6.3320684e+10 | F33: Moderate
B34: -5 days | C34: =INDEX('02_Assumptions'!C:C,MATCH("∆CCC scenario 1 (days)",'02_Assumptions'!B:B,0)) -> -5 | D34: =-C34*E27 -> 3.1660342e+10 | F34: Modest
B35: 0 (base) | C35: =0 -> 0 | D35: =-C35*E27 -> 0 | F35: Current position
B36: +5 days (worst case) | C36: =INDEX('02_Assumptions'!C:C,MATCH("∆CCC scenario 4 (days)",'02_Assumptions'!B:B,0)) -> 5 | D36: =-C36*E27 -> -3.1660342e+10 | F36: Deterioration
B39: E. FY2022 OPENING BALANCES (for average-balance computation of FY2023)
B40: Balance at 31/12/2022 | C40: VND
B41: Trade receivables (TK 131) - FY2022 | C41: 350602580193
B42: Inventory total (MS 140) - FY2022 | C42: 366595376460
B43: Trade payables (TK 311) - FY2022 | C43: 277697540107
B47: F. DPO CROSS-CHECK ON A PURCHASES BASIS
B48: Metric | C48: FY2023 | D48: FY2024 | E48: FY2025
B49: Purchases = COGS + change in inventory | C49: =C8+(INDEX('03_FS_Restated'!C:C,MATCH("Inventory — Total",'03_FS_Restated'!B:B,0))-C42) -> 1600645295156 | D49: =D8+(INDEX('03_FS_Restated'!D:D,MATCH("Inventory — Total",'03_FS_Restated'!B:B,0))-INDEX('03_FS_Restated'!C:C,MATCH("Inventory — Total",'03_FS_Restated'!B:B,0))) -> 1694427494492 | E49: =E8+(INDEX('03_FS_Restated'!E:E,MATCH("Inventory — Total",'03_FS_Restated'!B:B,0))-INDEX('03_FS_Restated'!D:D,MATCH("Inventory — Total",'03_FS_Restated'!B:B,0))) -> 1932697964803
B50: DPO (purchases basis) | C50: =IFERROR(C15/C49*365,0) -> 46.080716 | D50: =IFERROR(D15/D49*365,0) -> 29.938357 | E50: =IFERROR(E15/E49*365,0) -> 31.673189

Sheet 06_Peer_Inputs
B2: 06 - PEER INPUTS (as reported, own currency)
B5: A. PEER SET DEFINITION
B6: Company | C6: Listing | D6: Currency / units | E6: FY end | F6: Standard | G6: Role in the analysis
B7: Nhua Ha Noi | C7: HNX: NHH | D7: VND / dong | E7: 31/12 | F7: VAS (Circular 200) | G7: SUBJECT
B8: SKP Resources Bhd | C8: Bursa: SKP | D8: MYR / RM'000 | E8: 31/03 | F8: MFRS (IFRS-aligned) | G8: OEM structural peer - Dyson c.70% of revenue
B9: Sanko Gosei Ltd | C9: TSE: 7888 | D9: JPY / JPY mn | E9: 31/05 | F9: JGAAP | G9: OEM structural peer - moulding + mould dies, no >10% customer
B10: Nolato AB | C10: STO: NOLA-B | D10: SEK / SEK mn | E10: 31/12 | F10: IFRS | G10: Global polymer contract manufacturer - best-practice benchmark
B11: Nhua Tien Phong | C11: HNX: NTP | D11: VND / dong | E11: 31/12 | F11: VAS (Circular 200) | G11: Domestic control - distribution model
B12: An Phat Bioplastics | C12: HOSE: AAA | D12: VND / dong | E12: 31/12 | F12: VAS (Circular 200) | G12: RELATED PARTY - excluded from medians
B14: AAA is excluded from all peer medians: AAA raised its holding in NHH from 47.44% to 62.75% on 26/09/2024 and now consolidates NHH as a subsidiary. Comparing NHH with AAA from FY2025 compares NHH with a group that contains NHH.
B15: Fiscal years are not aligned. SKP closes 31/03 and Sanko closes 31/05, so their FY2025 columns overlap mainly with calendar 2024. Comparisons are made on a fiscal-year-as-reported basis; this is a stated limitation, not an adjustment.
B17: B.1 Nhua Ha Noi (dong)
B18: Line item | C18: FY2022 | D18: FY2023 | E18: FY2024 | F18: FY2025 | G18: Source note
B19: Trade receivables (net) | C19: 350602580193 | D19: 225698917511 | E19: 298853660085 | F19: 281041557777
B20: Inventory (net) | C20: 366595376460 | D20: 230582555144 | E20: 218749159456 | F20: 239364939489
B21: Trade payables | C21: 277697540107 | D21: 126460714750 | E21: 151502988335 | F21: 183920068898
B22: Revenue (net) | C22: 2383164448728 | D22: 2039284758153 | E22: 2096905452640 | F22: 2311204952919
B23: Cost of goods sold | C23: 1969409126016 | D23: 1736658116472 | E23: 1706260890180 | F23: 1912082184770
B24: Total equity | C24: 1301714680301 | D24: 1373217933338 | E24: 1356545653310 | F24: 1825602815409
B25: Net income | C25: 111926036003 | D25: 96243253037 | E25: 87854703191 | F25: 119627869202
B26: Interest expense | C26: 43547184624 | D26: 45942326390 | E26: 21203575185 | F26: 16100394821
B27: Trade receivables = TK 131 only. Inventory = MS 140, net of provision TK 159. Trade payables = TK 311.
B29: B.2 SKP Resources Bhd (RM'000)
B30: Line item | C30: FY2022 | D30: FY2023 | E30: FY2024 | F30: FY2025 | G30: Source note
B31: Trade receivables (net) | C31: 515311 | D31: 462195 | E31: 442117 | F31: 537849
B32: Inventory (net) | C32: 254658 | D32: 252836 | E32: 187481 | F32: 214288
B33: Trade payables | C33: 375745 | D33: 304535 | E33: 324123 | F33: 354467
B34: Revenue (net) | C34: 2321428 | D34: 2515038 | E34: 1852307 | F34: 2222635
B35: Cost of goods sold | C35: 1996602 | D35: 2195377 | E35: 1609329 | F35: 1959203
B36: Total equity | C36: 814514 | D36: 868321 | E36: 889004 | F36: 960413
B37: Net income | C37: 173396 | D37: 140518 | E37: 90989 | F37: 117030
B38: Interest expense | C38: 177 | D38: 1716 | E38: 3082 | F38: 7784
B39: Trade payables are reported as "Trade and other payables" and cannot be split. DPO for SKP is therefore an UPPER BOUND.
B41: B.3 Sanko Gosei Ltd (JPY mn)
B42: Line item | C42: FY2022 | D42: FY2023 | E42: FY2024 | F42: FY2025
B43: Trade receivables (net) | C43: 14670 | D43: 16871 | E43: 19706 | F43: 17082
B44: Inventory (net) | C44: 6979 | D44: 7665 | E44: 8357 | F44: 7881
B45: o/w raw materials | C45: 1777 | D45: 1763 | E45: 1956 | F45: 2066
B46: o/w work in progress | C46: 3306 | D46: 4580 | E46: 4340 | F46: 4044
B47: o/w finished goods | C47: 1896 | D47: 1322 | E47: 2061 | F47: 1771
B48: Trade payables | C48: 9548 | D48: 11734 | E48: 12134 | F48: 11766
B49: Revenue (net) | C49: 65661 | D49: 81113 | E49: 93784 | F49: 91101
B50: Cost of goods sold | C50: 55956 | D50: 69622 | E50: 80406 | F50: 76080
B51: Total equity | C51: 23251 | D51: 25950 | E51: 30479 | F51: 32779
B52: Net income | C52: 1811 | D52: 2096 | E52: 2612 | F52: 3857
B53: Interest expense | C53: 361 | D53: 368 | E53: 456 | F53: 474
B54: Trade receivables = notes receivable + electronically recorded monetary claims + accounts receivable. Trade payables = notes and accounts payable - trade + electronically recorded obligations. Omitting the electronic lines would understate both.
B56: B.4 Nolato AB (SEK mn)
B57: Line item | C57: FY2022 | D57: FY2023 | E57: FY2024 | F57: FY2025
B58: Trade receivables (net) | C58: 1522 | D58: 1525 | E58: 1558 | F58: 1600
B59: Inventory (net) | C59: 1283 | D59: 1196 | E59: 1183 | F59: 1086
B60: Trade payables | C60: 779 | D60: 620 | E60: 704 | F60: 646
B61: Revenue (net) | C61: 10774 | D61: 9546 | E61: 9664 | F61: 9462
B62: Cost of goods sold | D62: 8210 | E62: 8051 | F62: 7732
B63: Total equity | C63: 5392 | D63: 5171 | E63: 5738 | F63: 5532
B64: Net income | C64: 697 | D64: 435 | E64: 658 | F64: 777
B65: Interest expense | E65: 60 | F65: 46
B66: FY2022 COGS and FY2022-23 interest expense are not disclosed in the segments retrieved; FY2022 P&L is not required because only balance-sheet FY2022 feeds the averages.
B68: B.5 Nhua Tien Phong (dong)
B69: Line item | C69: FY2022 | D69: FY2023 | E69: FY2024 | F69: FY2025
B70: Trade receivables (net) | C70: 866425088081 | D70: 869315928192 | E70: 388318659135 | F70: 374391953022
B71: Inventory (net) | C71: 1535149437534 | D71: 1158634823678 | E71: 1005126876948 | F71: 1441053821794
B72: Trade payables | C72: 287076377670 | D72: 313255093379 | E72: 313880517607 | F72: 276189676959
B73: Revenue (net) | C73: 5685112416767 | D73: 5175862669587 | E73: 5656563814495 | F73: 6750824646188
B74: Cost of goods sold | C74: 4294534288942 | D74: 3619645131711 | E74: 3886614549588 | F74: 4658204795059
B75: Total equity | C75: 2830817344826 | D75: 3115499287238 | E75: 3666374210005 | F75: 4231801014628
B76: Net income | C76: 479539723632 | D76: 559414720517 | E76: 735659511537 | F76: 992866044209
B77: Interest expense | C77: 78639277456 | D77: 90107847382 | E77: 48945955598 | F77: 80323575442
B78: Trade receivables = TK 131 gross. Business model is distribution through dealers, not OEM contract manufacturing.
B80: B.6 An Phat Bioplastics (dong)
B81: Line item | C81: FY2022 | D81: FY2023 | E81: FY2024 | F81: FY2025
B82: Trade receivables (net) | C82: 1020327735573 | D82: 687000734407 | E82: 1205499960149 | F82: 703466021715
B83: Inventory (net) | C83: 1790091357848 | D83: 781680229197 | E83: 1286443372106 | F83: 943451289416
B84: Trade payables | C84: 754557899880 | D84: 517381867012 | E84: 873489122186 | F84: 587551921350
B85: Revenue (net) | C85: 15290297073087 | D85: 12621514144947 | E85: 12782230561048 | F85: 10728147400851
B86: Cost of goods sold | C86: 14204057189374 | D86: 11512820822177 | E86: 11298125054883 | F86: 9235313962502
B87: Total equity | C87: 6171185417465 | D87: 5963870940230 | E87: 6236273953200 | F87: 6079230359763
B88: Net income | C88: 117291267937 | D88: 309193823134 | E88: 319781840731 | F88: 423921411857
B89: Interest expense | C89: 173679772675 | D89: 190476045845 | E89: 159525373952 | F89: 133833486614
B90: Trade receivables = TK 131 gross. Allowance TK 137 covers all short-term receivables and is not netted.

Sheet 07_Peer_Benchmark
B2: 07 - PEER BENCHMARK: CASH CONVERSION CYCLE
B5: A. CCC DECOMPOSITION BY COMPANY
B6: Company / metric | C6: FY2023 | D6: FY2024 | E6: FY2025 | G6: Change FY23-25 | J6: Comment
B7: Nhua Ha Noi (HNX: NHH)
B8: DSO | C8: =IFERROR((('06_Peer_Inputs'!C19+'06_Peer_Inputs'!D19)/2)/'06_Peer_Inputs'!D22*365,"") -> 51.574466 | D8: =IFERROR((('06_Peer_Inputs'!D19+'06_Peer_Inputs'!E19)/2)/'06_Peer_Inputs'!E22*365,"") -> 45.653391 | E8: =IFERROR((('06_Peer_Inputs'!E19+'06_Peer_Inputs'!F19)/2)/'06_Peer_Inputs'!F22*365,"") -> 45.790347 | G8: =IFERROR(E8-C8,"") -> -5.7841192
B9: DIO | C9: =IFERROR((('06_Peer_Inputs'!C20+'06_Peer_Inputs'!D20)/2)/'06_Peer_Inputs'!D23*365,"") -> 62.755571 | D9: =IFERROR((('06_Peer_Inputs'!D20+'06_Peer_Inputs'!E20)/2)/'06_Peer_Inputs'!E23*365,"") -> 48.060082 | E9: =IFERROR((('06_Peer_Inputs'!E20+'06_Peer_Inputs'!F20)/2)/'06_Peer_Inputs'!F23*365,"") -> 43.725015 | G9: =IFERROR(E9-C9,"") -> -19.030556
B10: DPO | C10: =IFERROR((('06_Peer_Inputs'!C21+'06_Peer_Inputs'!D21)/2)/'06_Peer_Inputs'!D23*365,"") -> 42.471734 | D10: =IFERROR((('06_Peer_Inputs'!D21+'06_Peer_Inputs'!E21)/2)/'06_Peer_Inputs'!E23*365,"") -> 29.730726 | E10: =IFERROR((('06_Peer_Inputs'!E21+'06_Peer_Inputs'!F21)/2)/'06_Peer_Inputs'!F23*365,"") -> 32.014685 | G10: =IFERROR(E10-C10,"") -> -10.457049
B11: CCC | C11: =IFERROR(C8+C9-C10,"") -> 71.858304 | D11: =IFERROR(D8+D9-D10,"") -> 63.982747 | E11: =IFERROR(E8+E9-E10,"") -> 57.500678 | G11: =IFERROR(E11-C11,"") -> -14.357626 | J11: SUBJECT
B13: SKP Resources Bhd (Bursa: SKP)
B14: DSO | C14: =IFERROR((('06_Peer_Inputs'!C31+'06_Peer_Inputs'!D31)/2)/'06_Peer_Inputs'!D34*365,"") -> 70.931272 | D14: =IFERROR((('06_Peer_Inputs'!D31+'06_Peer_Inputs'!E31)/2)/'06_Peer_Inputs'!E34*365,"") -> 89.098049 | E14: =IFERROR((('06_Peer_Inputs'!E31+'06_Peer_Inputs'!F31)/2)/'06_Peer_Inputs'!F34*365,"") -> 80.464761 | G14: =IFERROR(E14-C14,"") -> 9.5334892
B15: DIO | C15: =IFERROR((('06_Peer_Inputs'!C32+'06_Peer_Inputs'!D32)/2)/'06_Peer_Inputs'!D35*365,"") -> 42.187586 | D15: =IFERROR((('06_Peer_Inputs'!D32+'06_Peer_Inputs'!E32)/2)/'06_Peer_Inputs'!E35*365,"") -> 49.93252 | E15: =IFERROR((('06_Peer_Inputs'!E32+'06_Peer_Inputs'!F32)/2)/'06_Peer_Inputs'!F35*365,"") -> 37.424832 | G15: =IFERROR(E15-C15,"") -> -4.7627539
B16: DPO | C16: =IFERROR((('06_Peer_Inputs'!C33+'06_Peer_Inputs'!D33)/2)/'06_Peer_Inputs'!D35*365,"") -> 56.551153 | D16: =IFERROR((('06_Peer_Inputs'!D33+'06_Peer_Inputs'!E33)/2)/'06_Peer_Inputs'!E35*365,"") -> 71.290634 | E16: =IFERROR((('06_Peer_Inputs'!E33+'06_Peer_Inputs'!F33)/2)/'06_Peer_Inputs'!F35*365,"") -> 63.210742 | G16: =IFERROR(E16-C16,"") -> 6.6595891
B17: CCC | C17: =IFERROR(C14+C15-C16,"") -> 56.567705 | D17: =IFERROR(D14+D15-D16,"") -> 67.739935 | E17: =IFERROR(E14+E15-E16,"") -> 54.678851 | G17: =IFERROR(E17-C17,"") -> -1.8888538 | J17: OEM structural peer - Dyson c.70% of revenue
B19: Sanko Gosei Ltd (TSE: 7888)
B20: DSO | C20: =IFERROR((('06_Peer_Inputs'!C43+'06_Peer_Inputs'!D43)/2)/'06_Peer_Inputs'!D49*365,"") -> 70.965597 | D20: =IFERROR((('06_Peer_Inputs'!D43+'06_Peer_Inputs'!E43)/2)/'06_Peer_Inputs'!E49*365,"") -> 71.177413 | E20: =IFERROR((('06_Peer_Inputs'!E43+'06_Peer_Inputs'!F43)/2)/'06_Peer_Inputs'!F49*365,"") -> 73.696337 | G20: =IFERROR(E20-C20,"") -> 2.7307397
B21: DIO | C21: =IFERROR((('06_Peer_Inputs'!C44+'06_Peer_Inputs'!D44)/2)/'06_Peer_Inputs'!D50*365,"") -> 38.386286 | D21: =IFERROR((('06_Peer_Inputs'!D44+'06_Peer_Inputs'!E44)/2)/'06_Peer_Inputs'!E50*365,"") -> 36.365632 | E21: =IFERROR((('06_Peer_Inputs'!E44+'06_Peer_Inputs'!F44)/2)/'06_Peer_Inputs'!F50*365,"") -> 38.951564 | G21: =IFERROR(E21-C21,"") -> 0.5652782
B22: DPO | C22: =IFERROR((('06_Peer_Inputs'!C48+'06_Peer_Inputs'!D48)/2)/'06_Peer_Inputs'!D50*365,"") -> 55.786461 | D22: =IFERROR((('06_Peer_Inputs'!D48+'06_Peer_Inputs'!E48)/2)/'06_Peer_Inputs'!E50*365,"") -> 54.173942 | E22: =IFERROR((('06_Peer_Inputs'!E48+'06_Peer_Inputs'!F48)/2)/'06_Peer_Inputs'!F50*365,"") -> 57.331099 | G22: =IFERROR(E22-C22,"") -> 1.5446377
B23: CCC | C23: =IFERROR(C20+C21-C22,"") -> 53.565422 | D23: =IFERROR(D20+D21-D22,"") -> 53.369103 | E23: =IFERROR(E20+E21-E22,"") -> 55.316802 | G23: =IFERROR(E23-C23,"") -> 1.7513802 | J23: OEM structural peer - moulding + mould dies, no >10% customer
B25: Nolato AB (STO: NOLA-B)
B26: DSO | C26: =IFERROR((('06_Peer_Inputs'!C58+'06_Peer_Inputs'!D58)/2)/'06_Peer_Inputs'!D61*365,"") -> 58.252409 | D26: =IFERROR((('06_Peer_Inputs'!D58+'06_Peer_Inputs'!E58)/2)/'06_Peer_Inputs'!E61*365,"") -> 58.220975 | E26: =IFERROR((('06_Peer_Inputs'!E58+'06_Peer_Inputs'!F58)/2)/'06_Peer_Inputs'!F61*365,"") -> 60.910484 | G26: =IFERROR(E26-C26,"") -> 2.6580747
B27: DIO | C27: =IFERROR((('06_Peer_Inputs'!C59+'06_Peer_Inputs'!D59)/2)/'06_Peer_Inputs'!D62*365,"") -> 55.105664 | D27: =IFERROR((('06_Peer_Inputs'!D59+'06_Peer_Inputs'!E59)/2)/'06_Peer_Inputs'!E62*365,"") -> 53.927152 | E27: =IFERROR((('06_Peer_Inputs'!E59+'06_Peer_Inputs'!F59)/2)/'06_Peer_Inputs'!F62*365,"") -> 53.555678 | G27: =IFERROR(E27-C27,"") -> -1.5499861
B28: DPO | C28: =IFERROR((('06_Peer_Inputs'!C60+'06_Peer_Inputs'!D60)/2)/'06_Peer_Inputs'!D62*365,"") -> 31.098356 | D28: =IFERROR((('06_Peer_Inputs'!D60+'06_Peer_Inputs'!E60)/2)/'06_Peer_Inputs'!E62*365,"") -> 30.012421 | E28: =IFERROR((('06_Peer_Inputs'!E60+'06_Peer_Inputs'!F60)/2)/'06_Peer_Inputs'!F62*365,"") -> 31.86433 | G28: =IFERROR(E28-C28,"") -> 0.76597439
B29: CCC | C29: =IFERROR(C26+C27-C28,"") -> 82.259718 | D29: =IFERROR(D26+D27-D28,"") -> 82.135706 | E29: =IFERROR(E26+E27-E28,"") -> 82.601832 | G29: =IFERROR(E29-C29,"") -> 0.34211414 | J29: Global polymer contract manufacturer - best-practice benchmark
B31: Nhua Tien Phong (HNX: NTP)
B32: DSO | C32: =IFERROR((('06_Peer_Inputs'!C70+'06_Peer_Inputs'!D70)/2)/'06_Peer_Inputs'!D73*365,"") -> 61.20192 | D32: =IFERROR((('06_Peer_Inputs'!D70+'06_Peer_Inputs'!E70)/2)/'06_Peer_Inputs'!E73*365,"") -> 40.575572 | E32: =IFERROR((('06_Peer_Inputs'!E70+'06_Peer_Inputs'!F70)/2)/'06_Peer_Inputs'!F73*365,"") -> 20.618916 | G32: =IFERROR(E32-C32,"") -> -40.583004
B33: DIO | C33: =IFERROR((('06_Peer_Inputs'!C71+'06_Peer_Inputs'!D71)/2)/'06_Peer_Inputs'!D74*365,"") -> 135.81874 | D33: =IFERROR((('06_Peer_Inputs'!D71+'06_Peer_Inputs'!E71)/2)/'06_Peer_Inputs'!E74*365,"") -> 101.60167 | E33: =IFERROR((('06_Peer_Inputs'!E71+'06_Peer_Inputs'!F71)/2)/'06_Peer_Inputs'!F74*365,"") -> 95.836915 | G33: =IFERROR(E33-C33,"") -> -39.981821
B34: DPO | C34: =IFERROR((('06_Peer_Inputs'!C72+'06_Peer_Inputs'!D72)/2)/'06_Peer_Inputs'!D74*365,"") -> 30.268297 | D34: =IFERROR((('06_Peer_Inputs'!D72+'06_Peer_Inputs'!E72)/2)/'06_Peer_Inputs'!E74*365,"") -> 29.4478 | E34: =IFERROR((('06_Peer_Inputs'!E72+'06_Peer_Inputs'!F72)/2)/'06_Peer_Inputs'!F74*365,"") -> 23.117878 | G34: =IFERROR(E34-C34,"") -> -7.1504188
B35: CCC | C35: =IFERROR(C32+C33-C34,"") -> 166.75236 | D35: =IFERROR(D32+D33-D34,"") -> 112.72944 | E35: =IFERROR(E32+E33-E34,"") -> 93.337953 | G35: =IFERROR(E35-C35,"") -> -73.414407 | J35: Domestic control - distribution model
B37: An Phat Bioplastics (HOSE: AAA)
B38: DSO | C38: =IFERROR((('06_Peer_Inputs'!C82+'06_Peer_Inputs'!D82)/2)/'06_Peer_Inputs'!D85*365,"") -> 24.68701 | D38: =IFERROR((('06_Peer_Inputs'!D82+'06_Peer_Inputs'!E82)/2)/'06_Peer_Inputs'!E85*365,"") -> 27.020431 | E38: =IFERROR((('06_Peer_Inputs'!E82+'06_Peer_Inputs'!F82)/2)/'06_Peer_Inputs'!F85*365,"") -> 32.47404 | G38: =IFERROR(E38-C38,"") -> 7.7870304
B39: DIO | C39: =IFERROR((('06_Peer_Inputs'!C83+'06_Peer_Inputs'!D83)/2)/'06_Peer_Inputs'!D86*365,"") -> 40.767447 | D39: =IFERROR((('06_Peer_Inputs'!D83+'06_Peer_Inputs'!E83)/2)/'06_Peer_Inputs'!E86*365,"") -> 33.406654 | E39: =IFERROR((('06_Peer_Inputs'!E83+'06_Peer_Inputs'!F83)/2)/'06_Peer_Inputs'!F86*365,"") -> 44.06518 | G39: =IFERROR(E39-C39,"") -> 3.2977332
B40: DPO | C40: =IFERROR((('06_Peer_Inputs'!C84+'06_Peer_Inputs'!D84)/2)/'06_Peer_Inputs'!D86*365,"") -> 20.162653 | D40: =IFERROR((('06_Peer_Inputs'!D84+'06_Peer_Inputs'!E84)/2)/'06_Peer_Inputs'!E86*365,"") -> 22.46691 | E40: =IFERROR((('06_Peer_Inputs'!E84+'06_Peer_Inputs'!F84)/2)/'06_Peer_Inputs'!F86*365,"") -> 28.871784 | G40: =IFERROR(E40-C40,"") -> 8.7091314
B41: CCC | C41: =IFERROR(C38+C39-C40,"") -> 45.291804 | D41: =IFERROR(D38+D39-D40,"") -> 37.960175 | E41: =IFERROR(E38+E39-E40,"") -> 47.667437 | G41: =IFERROR(E41-C41,"") -> 2.3756322 | J41: RELATED PARTY - excluded from medians
B43: SKP trade payables include non-trade items, so SKP DPO is an upper bound and its CCC is a lower bound. This is disclosed rather than adjusted, because no split is available in any SKP annual report.
B45: B. NHH VERSUS THE OEM CONTRACT-MANUFACTURING PEER GROUP (SKP, Sanko)
B46: Metric, FY2025 | C46: NHH | D46: SKP | E46: Sanko | G46: OEM mean | H46: Gap NHH vs OEM | J46: Reading
B47: DSO | C47: =E8 -> 45.790347 | D47: =E14 -> 80.464761 | E47: =E20 -> 73.696337 | G47: =AVERAGE(D47,E47) -> 77.080549 | H47: =C47-G47 -> -31.290202 | J47: NHH collects markedly faster than either OEM peer. Receivables are not the constraint.
B48: DIO | C48: =E9 -> 43.725015 | D48: =E15 -> 37.424832 | E48: =E21 -> 38.951564 | G48: =AVERAGE(D48,E48) -> 38.188198 | H48: =C48-G48 -> 5.5368175 | J48: NHH holds less inventory than Nolato but is broadly in line with the OEM peers.
B49: DPO | C49: =E10 -> 32.014685 | D49: =E16 -> 63.210742 | E49: =E22 -> 57.331099 | G49: =AVERAGE(D49,E49) -> 60.27092 | H49: =C49-G49 -> -28.256236 | J49: NHH pays suppliers far sooner than either OEM peer. This is the single largest structural gap.
B50: CCC | C50: =E11 -> 57.500678 | D50: =E17 -> 54.678851 | E50: =E23 -> 55.316802 | G50: =AVERAGE(D50,E50) -> 54.997827 | H50: =C50-G50 -> 2.5028513 | J50: Headline CCC is close to peers, but the composition is inverted: NHH funds its suppliers instead of being funded by them.
B52: C. QUANTIFYING THE PAYABLES GAP (FY2025, VND)
B53: Item | C53: Value | D53: Unit | J53: Basis
B54: NHH COGS, FY2025 | C54: ='06_Peer_Inputs'!F23 -> 1912082184770 | D54: VND | J54: Denominator for DPO
B55: One day of DPO | C55: =C54/365 -> 5.2385813e+09 | D55: VND | J55: COGS / 365
B56: NHH DPO, FY2025 | C56: =C49 -> 32.014685 | D56: days | J56: From section A
B57: OEM mean DPO, FY2025 | C57: =G49 -> 60.27092 | D57: days | J57: Mean of SKP and Sanko
B58: Payables gap | C58: =C57-C56 -> 28.256236 | D58: days | J58: Peer mean less NHH
B59: Cash that would be released if NHH closed the gap | C59: =C58*C55 -> 1.4802259e+11 | D59: VND | J59: Gap in days x one day of DPO
B60: NHH interest expense, FY2025 | C60: ='06_Peer_Inputs'!F26 -> 16100394821 | D60: VND | J60: Reported finance cost
B61: Implied cost of debt | C61: ='04_Ratios'!E46 -> 0.050549287 | D61: p.a. | J61: Linked from 04_Ratios: interest expense / average gross debt
B62: Annual interest saved on released cash | C62: =C59*C61 -> 7.4824364e+09 | D62: VND | J62: Released cash x cost of debt
B64: The gap is an indication of headroom, not a target. Part of it is structural: Japanese suppliers settle a large share of payables by note, and Malaysian reported payables include non-trade items. A realistic NHH objective would capture a portion of the gap, not all of it.
B66: D. CONTEXT RATIOS, FY2025
B67: Company | C67: Gross margin | D67: Net margin | E67: ROE | F67: Interest / revenue | J67: Note
B68: Nhua Ha Noi | C68: =IFERROR(('06_Peer_Inputs'!F22-'06_Peer_Inputs'!F23)/'06_Peer_Inputs'!F22,"") -> 0.17269034 | D68: =IFERROR('06_Peer_Inputs'!F25/'06_Peer_Inputs'!F22,"") -> 0.051759957 | E68: =IFERROR('06_Peer_Inputs'!F25/(('06_Peer_Inputs'!E24+'06_Peer_Inputs'!F24)/2),"") -> 0.075186856 | F68: =IFERROR('06_Peer_Inputs'!F26/'06_Peer_Inputs'!F22,"") -> 0.0069662341
B69: SKP Resources Bhd | C69: =IFERROR(('06_Peer_Inputs'!F34-'06_Peer_Inputs'!F35)/'06_Peer_Inputs'!F34,"") -> 0.11852238 | D69: =IFERROR('06_Peer_Inputs'!F37/'06_Peer_Inputs'!F34,"") -> 0.05265372 | E69: =IFERROR('06_Peer_Inputs'!F37/(('06_Peer_Inputs'!E36+'06_Peer_Inputs'!F36)/2),"") -> 0.1265588 | F69: =IFERROR('06_Peer_Inputs'!F38/'06_Peer_Inputs'!F34,"") -> 0.0035021495
B70: Sanko Gosei Ltd | C70: =IFERROR(('06_Peer_Inputs'!F49-'06_Peer_Inputs'!F50)/'06_Peer_Inputs'!F49,"") -> 0.16488293 | D70: =IFERROR('06_Peer_Inputs'!F52/'06_Peer_Inputs'!F49,"") -> 0.042337625 | E70: =IFERROR('06_Peer_Inputs'!F52/(('06_Peer_Inputs'!E51+'06_Peer_Inputs'!F51)/2),"") -> 0.12194505 | F70: =IFERROR('06_Peer_Inputs'!F53/'06_Peer_Inputs'!F49,"") -> 0.0052030164
B71: Nolato AB | C71: =IFERROR(('06_Peer_Inputs'!F61-'06_Peer_Inputs'!F62)/'06_Peer_Inputs'!F61,"") -> 0.18283661 | D71: =IFERROR('06_Peer_Inputs'!F64/'06_Peer_Inputs'!F61,"") -> 0.082117945 | E71: =IFERROR('06_Peer_Inputs'!F64/(('06_Peer_Inputs'!E63+'06_Peer_Inputs'!F63)/2),"") -> 0.1378882 | F71: =IFERROR('06_Peer_Inputs'!F65/'06_Peer_Inputs'!F61,"") -> 0.0048615515
B72: Nhua Tien Phong | C72: =IFERROR(('06_Peer_Inputs'!F73-'06_Peer_Inputs'!F74)/'06_Peer_Inputs'!F73,"") -> 0.30997989 | D72: =IFERROR('06_Peer_Inputs'!F76/'06_Peer_Inputs'!F73,"") -> 0.1470733 | E72: =IFERROR('06_Peer_Inputs'!F76/(('06_Peer_Inputs'!E75+'06_Peer_Inputs'!F75)/2),"") -> 0.25141657 | F72: =IFERROR('06_Peer_Inputs'!F77/'06_Peer_Inputs'!F73,"") -> 0.011898335
B73: An Phat Bioplastics | C73: =IFERROR(('06_Peer_Inputs'!F85-'06_Peer_Inputs'!F86)/'06_Peer_Inputs'!F85,"") -> 0.13915109 | D73: =IFERROR('06_Peer_Inputs'!F88/'06_Peer_Inputs'!F85,"") -> 0.039514876 | E73: =IFERROR('06_Peer_Inputs'!F88/(('06_Peer_Inputs'!E87+'06_Peer_Inputs'!F87)/2),"") -> 0.068843533 | F73: =IFERROR('06_Peer_Inputs'!F89/'06_Peer_Inputs'!F85,"") -> 0.012474986 | J73: Related party - shown for completeness only

Sheet 08_Dashboard
B2: EXECUTIVE DASHBOARD - NHH WORKING CAPITAL
B3: Cash Conversion Cycle diagnostic, FY2023-FY2025, benchmarked against listed plastics contract manufacturers.
B5: A. HEADLINE, FY2025
B6: CASH CONVERSION CYCLE (days) | D6: CCC IMPROVEMENT FY2023-25 (days) | G6: PAYABLES GAP VS OEM PEERS (days)
B7: =INDEX('05_CCC'!E:E,MATCH("CCC = DSO + DIO(Total) − DPO",'05_CCC'!B:B,0)) -> 57.500678 | D7: =INDEX('05_CCC'!E:E,MATCH("CCC = DSO + DIO(Total) − DPO",'05_CCC'!B:B,0))-INDEX('05_CCC'!C:C,MATCH("CCC = DSO + DIO(Total) − DPO",'05_CCC'!B:B,0)) -> -14.357626 | G7: ='07_Peer_Benchmark'!H49 -> -28.256236
B8: FY2023: see trend below | D8: Negative = cash released | G8: Negative = NHH pays sooner than peers
B10: WORKING CAPITAL TIED UP (VND) | D10: ONE DAY OF CCC (VND) | G10: CASH IF PAYABLES GAP CLOSED (VND)
B11: =INDEX('05_CCC'!E:E,MATCH("Working capital tied up = CCC x VND/day",'05_CCC'!B:B,0)) -> 3.6409822e+11 | D11: =INDEX('05_CCC'!E:E,MATCH("One day of CCC in VND = Revenue / 365",'05_CCC'!B:B,0)) -> 6.3320684e+09 | G11: ='07_Peer_Benchmark'!C59 -> 1.4802259e+11
B12: CCC x revenue per day | D12: Cash released per day of CCC | G12: Indicative headroom, not a target
B14: B. CCC TREND - NHH
B15: Metric | C15: FY2023 | D15: FY2024 | E15: FY2025 | F15: FY23-25
B16: DSO | C16: =INDEX('05_CCC'!C:C,MATCH("DSO — Days Sales Outstanding",'05_CCC'!B:B,0)) -> 51.574466 | D16: =INDEX('05_CCC'!D:D,MATCH("DSO — Days Sales Outstanding",'05_CCC'!B:B,0)) -> 45.653391 | E16: =INDEX('05_CCC'!E:E,MATCH("DSO — Days Sales Outstanding",'05_CCC'!B:B,0)) -> 45.790347 | F16: =E16-C16 -> -5.7841192
B17: DIO - total | C17: =INDEX('05_CCC'!C:C,MATCH("DIO — Total",'05_CCC'!B:B,0)) -> 62.755571 | D17: =INDEX('05_CCC'!D:D,MATCH("DIO — Total",'05_CCC'!B:B,0)) -> 48.060082 | E17: =INDEX('05_CCC'!E:E,MATCH("DIO — Total",'05_CCC'!B:B,0)) -> 43.725015 | F17: =E17-C17 -> -19.030556
B18: DPO | C18: =INDEX('05_CCC'!C:C,MATCH("DPO — Days Payable Outstanding",'05_CCC'!B:B,0)) -> 42.471734 | D18: =INDEX('05_CCC'!D:D,MATCH("DPO — Days Payable Outstanding",'05_CCC'!B:B,0)) -> 29.730726 | E18: =INDEX('05_CCC'!E:E,MATCH("DPO — Days Payable Outstanding",'05_CCC'!B:B,0)) -> 32.014685 | F18: =E18-C18 -> -10.457049
B19: CCC | C19: =INDEX('05_CCC'!C:C,MATCH("CCC = DSO + DIO(Total) − DPO",'05_CCC'!B:B,0)) -> 71.858304 | D19: =INDEX('05_CCC'!D:D,MATCH("CCC = DSO + DIO(Total) − DPO",'05_CCC'!B:B,0)) -> 63.982747 | E19: =INDEX('05_CCC'!E:E,MATCH("CCC = DSO + DIO(Total) − DPO",'05_CCC'!B:B,0)) -> 57.500678 | F19: =E19-C19 -> -14.357626
B21: C. PEER POSITION, FY2025
B22: Company | C22: DSO | D22: DIO | E22: DPO | F22: CCC
B23: Nhua Ha Noi | C23: ='07_Peer_Benchmark'!E8 -> 45.790347 | D23: ='07_Peer_Benchmark'!E9 -> 43.725015 | E23: ='07_Peer_Benchmark'!E10 -> 32.014685 | F23: ='07_Peer_Benchmark'!E11 -> 57.500678
B24: SKP Resources Bhd | C24: ='07_Peer_Benchmark'!E14 -> 80.464761 | D24: ='07_Peer_Benchmark'!E15 -> 37.424832 | E24: ='07_Peer_Benchmark'!E16 -> 63.210742 | F24: ='07_Peer_Benchmark'!E17 -> 54.678851
B25: Sanko Gosei Ltd | C25: ='07_Peer_Benchmark'!E20 -> 73.696337 | D25: ='07_Peer_Benchmark'!E21 -> 38.951564 | E25: ='07_Peer_Benchmark'!E22 -> 57.331099 | F25: ='07_Peer_Benchmark'!E23 -> 55.316802
B26: Nolato AB | C26: ='07_Peer_Benchmark'!E26 -> 60.910484 | D26: ='07_Peer_Benchmark'!E27 -> 53.555678 | E26: ='07_Peer_Benchmark'!E28 -> 31.86433 | F26: ='07_Peer_Benchmark'!E29 -> 82.601832
B27: Nhua Tien Phong | C27: ='07_Peer_Benchmark'!E32 -> 20.618916 | D27: ='07_Peer_Benchmark'!E33 -> 95.836915 | E27: ='07_Peer_Benchmark'!E34 -> 23.117878 | F27: ='07_Peer_Benchmark'!E35 -> 93.337953
B29: AAA is omitted from this table: it became the parent of NHH on 26/09/2024 and consolidates NHH from that date. See 06_Peer_Inputs.
B31: D. READING THE CHARTS
B32: NHH improved its cash conversion cycle by 14.4 days between FY2023 and FY2025, driven mainly by a 19.0 day reduction in inventory days.
B33: Headline CCC is now close to the OEM contract-manufacturing peers, but the composition is inverted: NHH collects about 31 days faster than the peer mean and pays about 28 days sooner.
B34: Nolato carries the highest CCC of the contract manufacturers at 82.6 days. A high cycle is not automatically poor management: its medical and pharmaceutical work requires deeper inventory and earns a wider margin.
B35: NTP sits far outside the group at 93.3 days with 95.8 inventory days, which is the signature of a distribution model holding stock for a dealer network rather than manufacturing to customer order.

Sheet 09_Reference
B2: 10 — REFERENCE: GLOSSARY, TK CODES, ASSUMPTIONS LOG
B4: A. GLOSSARY EN — VN — DEFINITION
B5: English | C5: Vietnamese | D5: Formula | E5: Notes
B6: CCC — Cash Conversion Cycle | C6: Cash conversion cycle | D6: DIO + DSO − DPO | E6: Measures the number of days cash is tied up in the operating cycle
B7: DIO — Days Inventory Outstanding | C7: Days inventory outstanding | D7: Avg Inventory / COGS × 365 | E7: For a contract manufacturer, split into raw materials, work in progress and finished goods
B8: DSO — Days Sales Outstanding | C8: Days sales outstanding | D8: Avg AR / Revenue × 365 | E8: Compare with the customer contractual payment terms
B9: DPO — Days Payable Outstanding | C9: Days payable outstanding | D9: Avg AP / COGS × 365 | E9: The higher the figure, the more supplier financing is being used
B10: NWC — Net Working Capital | C10: Net working capital | D10: Current Assets − Current Liab
B11: Operating NWC | C11: Operating working capital | D11: AR + Inventory − AP | E11: Excludes cash and debt
B12: COGS — Cost of Goods Sold | C12: Cost of goods sold | D12: TK 632
B13: EBITDA | C13: Earnings before interest, tax, depreciation and amortisation | D13: Operating profit + D&A
B14: ROIC — Return on Invested Capital | C14: Return on invested capital | D14: NOPAT / (Debt + Equity) | E14: Measures the return on all invested capital
B15: DuPont Analysis | C15: DuPont decomposition | D15: ROE = NM × AT × EM | E15: Net Margin × Asset Turnover × Equity Multiplier
B16: Pareto / ABC Analysis | C16: ABC classification on a Pareto basis | D16: 80/15/5 rule | E16: A is approximately 80% of value, B 15%, C 5%
B17: AR Aging | C17: Receivables ageing analysis | D17: Buckets by days past due | E17: 0-30/31-60/61-90/91-180/>180
B18: Rolling 13-week Forecast | C18: Rolling 13-week cash flow forecast | D18: Direct method | E18: Ref: Clauss Ch.8
B21: B. VAS / CIRCULAR 200 - KEY ACCOUNT CODES
B22: Account code | C22: Account name (Vietnamese, per Circular 200) | D22: Class | E22: Use in this project
B23: 111 | C23: Tiền mặt | D23: Current assets | E23: Cash forecast, Cash ratio
B24: 112 | C24: Tiền gửi ngân hàng | D24: Current assets | E24: Cash forecast base pattern
B25: 131 | C25: Phải thu khách hàng | D25: Current assets | E25: AR Aging, DSO
B26: 133 | C26: Thuế GTGT được khấu trừ | D26: Current assets
B27: 139 | C27: Dự phòng phải thu khó đòi | D27: Current assets (contra) | E27: Adjustment cho AR
B28: 152 | C28: Nguyên vật liệu (NVL) | D28: Inventory | E28: DIO NVL, ABC classification
B29: 153 | C29: Công cụ dụng cụ | D29: Inventory
B30: 154 | C30: Chi phí SXKD dở dang (WIP) | D30: Inventory | E30: DIO WIP — key cho job-order
B31: 155 | C31: Thành phẩm (FG) | D31: Inventory | E31: DIO FG
B32: 156 | C32: Hàng hóa | D32: Inventory
B33: 159 | C33: Dự phòng giảm giá tồn kho | D33: Inventory (contra)
B34: 211 | C34: Nguyên giá TSCĐ hữu hình | D34: Fixed assets
B35: 214 | C35: Hao mòn luỹ kế TSCĐ | D35: Fixed assets (contra) | E35: D&A source
B36: 331 | C36: Phải trả người bán | D36: Current liabilities | E36: DPO, Cash forecast supplier
B37: 333 | C37: Thuế và các khoản phải nộp NN | D37: Current liabilities | E37: Cash forecast tax outflow
B38: 334 | C38: Phải trả người lao động | D38: Current liabilities | E38: Cash forecast payroll outflow
B39: 341 | C39: Vay và nợ thuê tài chính | D39: Liabilities | E39: Debt / Equity, Interest coverage
B40: 411 | C40: Vốn góp của chủ sở hữu | D40: Equity
B41: 421 | C41: Lợi nhuận sau thuế chưa PP | D41: Equity
B42: 511 | C42: Doanh thu bán hàng và CCDV | D42: P&L | E42: Revenue
B43: 515 | C43: Doanh thu hoạt động tài chính | D43: P&L
B44: 632 | C44: Giá vốn hàng bán (COGS) | D44: P&L | E44: DIO, DPO, GP margin
B45: 635 | C45: Chi phí tài chính | D45: P&L | E45: Interest expense
B46: 641 | C46: Chi phí bán hàng | D46: P&L
B47: 642 | C47: Chi phí quản lý doanh nghiệp | D47: P&L
B48: 821 | C48: Chi phí thuế TNDN | D48: P&L | E48: Effective tax rate
B51: C. ASSUMPTIONS LOG - record of driver changes
B52: Date | C52: Driver changed | D52: From - To | E52: Reason
B65: D. METHODOLOGY NOTES - PEER BENCHMARK
B66: Basis. All ratios use average balances: (opening + closing) / 2. DSO is measured on revenue; DIO and DPO on cost of goods sold. 365 days per year.
B67: Currency. Figures are kept in each company reporting currency. CCC is expressed in days and is currency-neutral, so no FX translation is applied and no FX error is introduced.
B68: Fiscal-year alignment. NHH, AAA, NTP and Nolato close 31 December; SKP closes 31 March; Sanko closes 31 May. Comparisons are made on a fiscal-year-as-reported basis. Sanko and SKP FY2025 therefore overlap mainly with calendar 2024.
B69: Accounting standards. VAS (Circular 200/2014/TT-BTC) for the Vietnamese companies, MFRS for SKP, JGAAP for Sanko, IFRS for Nolato. Differences at the level of trade receivables, inventory and trade payables are immaterial to the cash conversion cycle.
B70: Japanese receivables and payables. Sanko discloses notes receivable and electronically recorded monetary claims separately from accounts receivable, and the mirror items on the payables side. All components are included; excluding them would understate both DSO and DPO by a wide margin.
B71: SKP payables. SKP reports trade and other payables as a single line in every annual report. Its DPO is therefore an upper bound and its CCC a lower bound. The limitation is disclosed rather than estimated away.
B72: Related-party exclusion. AAA increased its holding in NHH from 47.44% to 62.75% on 26 September 2024 and consolidates NHH from that date. AAA is retained in the input sheet for completeness but excluded from every peer average.
B73: Peer group construction. SKP and Sanko form the OEM contract-manufacturing comparator set: both manufacture plastic components to customer specification, and Sanko also operates a mould-die business, matching the NHH product mix. Nolato is a global best-practice reference. NTP is a domestic control that isolates the effect of the Vietnamese operating environment from the effect of the business model.
